{
  "info": {
    "key": "b9601_0218"
  },
  "sheets": {
    "מזומנים": {
      "columns": [
        "שם המנפיק/שם נייר ערך",
        "מספר ני\"ע",
        "מספר מנפיק",
        "דירוג",
        "שם מדרג",
        "סוג מטבע",
        "שיעור ריבית",
        "תשואה לפידיון",
        "שווי שוק",
        "שעור מנכסי אפיק ההשקעה",
        "שעור מסך נכסי השקעה"
      ],
      "data": [
        [
          "עו'ש - בנק הפועלים",
          "12- 1111111111",
          12,
          "AA+",
          "מעלות",
          "שקל חדש",
          0.0,
          0,
          0.31854000000000005,
          0.017781381812537963,
          0.001838718132575111
        ],
        [
          "דולר ארה\"ב - בנק הפועלים",
          "12- 19",
          12,
          "AA+",
          "מעלות",
          "דולר ארה\"ב",
          5.3,
          0,
          195.53729000000016,
          10.827229303065232,
          1.1196105597967076
        ],
        [
          "לי\"שט - בנק הפועלים",
          "12- 2",
          12,
          "AA+",
          "מעלות",
          "לי\"שט",
          0.0,
          0,
          68.53649,
          3.8258099352708923,
          0.39561526623360566
        ],
        [
          "פ.ח.ק. - בנק הפועלים",
          "12- 1111111110",
          12,
          "AA+",
          "מעלות",
          "שקל חדש",
          0.0,
          0,
          1528.6076799999998,
          85.32917937985134,
          8.823628614332806
        ]
      ]
    },
    "מניות": {
      "columns": [
        "שם המנפיק/שם נייר ערך",
        "מספר ני\"ע",
        "זירת מסחר",
        "ספק מידע",
        "מספר מנפיק",
        "ענף מסחר",
        "סוג מטבע",
        "ערך נקוב",
        "שער",
        "פדיון/ ריבית לקבל",
        "שווי שוק",
        "שעור מערך נקוב מונפק",
        "שעור מנכסי אפיק ההשקעה",
        "שעור מסך נכסי השקעה"
      ],
      "data": [
        [
          "אלביט מערכות",
          1081124,
          "TASE",
          "",
          520043027,
          "אלקטרוניקה ואופטיקה",
          "שקל חדש",
          1270.0,
          42930.0,
          2.00833,
          547.3323468700002,
          0.0,
          5.32,
          3.16
        ],
        [
          "נייס- נייס",
          273011,
          "TASE",
          "",
          520036872,
          "אלקטרוניקה ואופטיקה",
          "שקל חדש",
          1177.0,
          37760.0,
          0.0,
          444.4352,
          0.0,
          4.32,
          2.57
        ],
        [
          "הראל- הראל השקעות",
          585018,
          "TASE",
          "",
          520033986,
          "ביטוח",
          "שקל חדש",
          8549.0,
          2741.0,
          0.0,
          234.32809,
          0.0,
          2.28,
          1.35
        ],
        [
          "דיסקונט- בנק דיסקונט",
          691212,
          "TASE",
          "",
          520007030,
          "בנקים",
          "שקל חדש",
          33369.0,
          1067.0,
          0.0,
          356.04723,
          0.0,
          3.46,
          2.06
        ],
        [
          "5 בינלאומי- בנק הבינלאומי",
          593038,
          "TASE",
          "",
          520029083,
          "בנקים",
          "שקל חדש",
          2740.0,
          7635.0,
          0.0,
          209.199,
          0.0,
          2.03,
          1.21
        ],
        [
          "לאומי- בנק לאומי",
          604611,
          "TASE",
          "",
          520018078,
          "בנקים",
          "שקל חדש",
          24707.0,
          2160.0,
          0.0,
          533.6712,
          0.0,
          5.18,
          3.08
        ],
        [
          "מזרחי- בנק מזרחי טפחות",
          695437,
          "TASE",
          "",
          520032046,
          "בנקים",
          "שקל חדש",
          1541.0,
          6717.0,
          0.0,
          103.50897,
          0.0,
          1.01,
          0.6
        ],
        [
          "חברה לישראל- חברה לישראל",
          576017,
          "TASE",
          "",
          520028010,
          "השקעה ואחזקות",
          "שקל חדש",
          76.0,
          77850.0,
          0.0,
          59.166,
          0.0,
          0.57,
          0.34
        ],
        [
          "אורמת טכנולוגיות- אורמת",
          1134402,
          "TASE",
          "",
          520036716,
          "השקעות בהיי-טק",
          "שקל חדש",
          1748.0,
          19280.0,
          0.0,
          337.0144,
          0.0,
          3.27,
          1.95
        ],
        [
          "*דלק קדוחים יהש- דלק קידוחים",
          475020,
          "TASE",
          "",
          550013098,
          "חיפושי נפט וגז",
          "שקל חדש",
          2784.37,
          916.0,
          0.0,
          25.5048292,
          0.0,
          0.25,
          0.15
        ],
        [
          "ישראמקו יהש- ישראמקו נגב 2",
          232017,
          "TASE",
          "",
          550010003,
          "חיפושי נפט וגז",
          "שקל חדש",
          140000.0,
          37.6,
          0.0,
          52.64,
          0.0,
          0.51,
          0.3
        ],
        [
          "טבע- טבע",
          629014,
          "TASE",
          "",
          520013954,
          "כימיה, גומי ופלסטיק",
          "שקל חדש",
          4594.0,
          8683.0,
          0.0,
          398.89702,
          0.0,
          3.88,
          2.3
        ],
        [
          "כיל- כימיקלים לישראל",
          281014,
          "TASE",
          "",
          520027830,
          "כימיה, גומי ופלסטיק",
          "שקל חדש",
          28305.0,
          1670.0,
          0.0,
          472.6935,
          0.0,
          4.59,
          2.73
        ],
        [
          "פריגו פי אל סי- פריגו",
          1130699,
          "TASE",
          "",
          529592,
          "כימיה, גומי ופלסטיק",
          "שקל חדש",
          909.0,
          26790.0,
          0.0,
          243.5211,
          0.0,
          2.37,
          1.41
        ],
        [
          "טאואר- טאואר",
          1082379,
          "TASE",
          "",
          520041997,
          "מוליכים למחצה",
          "שקל חדש",
          1560.0,
          8106.0,
          0.0,
          126.4536,
          0.0,
          1.23,
          0.73
        ],
        [
          "סודהסטרים- SODA STREAM",
          1121300,
          "TASE",
          "",
          510999410,
          "מזון",
          "שקל חדש",
          1024.0,
          30620.0,
          0.0,
          313.5488,
          0.0,
          3.05,
          1.81
        ],
        [
          "פרוטרום- פרוטרום",
          1081082,
          "TASE",
          "",
          520042805,
          "מזון",
          "שקל חדש",
          753.0,
          35850.0,
          0.0,
          269.9505,
          0.0,
          2.62,
          1.56
        ],
        [
          "שטראוס עלית- שטראוס גרופ",
          746016,
          "TASE",
          "",
          520003781,
          "מזון",
          "שקל חדש",
          2095.0,
          7360.0,
          0.0,
          154.192,
          0.0,
          1.5,
          0.89
        ],
        [
          "שופרסל- שופרסל",
          777037,
          "TASE",
          "",
          520022732,
          "מסחר",
          "שקל חדש",
          10854.0,
          2242.0,
          0.0,
          243.34668,
          0.0,
          2.36,
          1.4
        ],
        [
          "אלוני חץ- אלוני חץ",
          390013,
          "TASE",
          "",
          520038506,
          "נדל\"ן ובינוי",
          "שקל חדש",
          3540.0,
          3360.0,
          0.0,
          118.944,
          0.0,
          1.16,
          0.69
        ],
        [
          "עזריאלי קבוצה- עזריאלי",
          1119478,
          "TASE",
          "",
          510960719,
          "נדל\"ן ובינוי",
          "שקל חדש",
          416.0,
          18140.0,
          0.0,
          75.4624,
          0.0,
          0.73,
          0.44
        ],
        [
          "בזק- בזק",
          230011,
          "TASE",
          "",
          520031931,
          "תקשורת ומדיה",
          "שקל חדש",
          49686.0,
          411.6,
          0.0,
          204.507576,
          0.0,
          1.99,
          1.18
        ],
        [
          "דלתא גליל- דלתא גליל",
          627034,
          "TASE",
          "",
          520025602,
          "אופנה והלבשה",
          "שקל חדש",
          5.0,
          10580.0,
          0.0,
          0.529,
          0.0,
          0.01,
          0.0
        ],
        [
          "המלט- המלט",
          1080324,
          "TASE",
          "",
          520041575,
          "אלקטרוניקה ואופטיקה",
          "שקל חדש",
          991.0,
          9422.0,
          0.0,
          93.37202,
          0.01,
          0.91,
          0.54
        ],
        [
          "איידיאיי ביטוח- איי די אי ביטוח",
          1129501,
          "TASE",
          "",
          512280058,
          "ביטוח",
          "שקל חדש",
          500.0,
          21940.0,
          0.0,
          109.7,
          0.0,
          1.07,
          0.63
        ],
        [
          "כלל ביטוח- כלל החזקות עסקי ביטוח",
          224014,
          "TASE",
          "",
          520036120,
          "ביטוח",
          "שקל חדש",
          483.0,
          5103.0,
          0.0,
          24.64749,
          0.0,
          0.24,
          0.14
        ],
        [
          "מגדל ביטוח- מגדל",
          1081165,
          "TASE",
          "",
          520029984,
          "ביטוח",
          "שקל חדש",
          6888.0,
          315.8,
          0.0,
          21.752304,
          0.0,
          0.21,
          0.13
        ],
        [
          "יואל- יואל",
          583013,
          "TASE",
          "",
          520033226,
          "השקעה ואחזקות",
          "שקל חדש",
          787.0,
          18570.0,
          0.0,
          146.1459,
          0.0,
          1.42,
          0.84
        ],
        [
          "רציו יהש- רציו חיפושי נפט ( 1992 ) -שותפות מוגבלת",
          394015,
          "TASE",
          "",
          550012777,
          "חיפושי נפט וגז",
          "שקל חדש",
          43666.75,
          227.5,
          0.0,
          99.34185625,
          0.0,
          0.97,
          0.57
        ],
        [
          "אנלייט אנרגיה- אנלייט",
          720011,
          "TASE",
          "",
          520041146,
          "חשמל",
          "שקל חדש",
          17982.0,
          185.9,
          0.0,
          33.428538,
          0.0,
          0.32,
          0.19
        ],
        [
          "פלסאון תעשיות- פלסאון",
          1081603,
          "TASE",
          "",
          520042912,
          "כימיה, גומי ופלסטיק",
          "שקל חדש",
          88.0,
          15550.0,
          0.0,
          13.684,
          0.0,
          0.13,
          0.08
        ],
        [
          "נובה- נובה",
          1084557,
          "TASE",
          "",
          511812463,
          "מוליכים למחצה",
          "שקל חדש",
          964.0,
          9998.0,
          0.0,
          96.38072,
          0.0,
          0.94,
          0.56
        ],
        [
          "אלקטרה צריכה- אלקטרה מוצרי צריכה",
          5010129,
          "TASE",
          "",
          520028911,
          "מסחר",
          "שקל חדש",
          900.0,
          4255.0,
          0.0,
          38.295,
          0.0,
          0.37,
          0.22
        ],
        [
          "סקופ- סקופ סחר מתכות",
          288019,
          "TASE",
          "",
          520037425,
          "מסחר",
          "שקל חדש",
          551.0,
          9851.0,
          0.0,
          54.27901,
          0.01,
          0.53,
          0.31
        ],
        [
          "רמי לוי- רמי לוי בע\"מ",
          1104249,
          "TASE",
          "",
          513770669,
          "מסחר",
          "שקל חדש",
          175.0,
          17740.0,
          0.0,
          31.045,
          0.0,
          0.3,
          0.18
        ],
        [
          "אדגר- אדגר",
          1820083,
          "TASE",
          "",
          520035171,
          "נדל\"ן ובינוי",
          "שקל חדש",
          4856.0,
          596.7,
          0.0,
          28.975752,
          0.0,
          0.28,
          0.17
        ],
        [
          "אלקטרה- אלקטרה",
          739037,
          "TASE",
          "",
          520028911,
          "נדל\"ן ובינוי",
          "שקל חדש",
          52.0,
          90910.0,
          0.0,
          47.2732,
          0.0,
          0.46,
          0.27
        ],
        [
          "ארקו החזקות- ארקו החזקות",
          310011,
          "TASE",
          "",
          520037367,
          "נדל\"ן ובינוי",
          "שקל חדש",
          9500.0,
          199.7,
          0.0,
          18.9715,
          0.0,
          0.18,
          0.11
        ],
        [
          "בראק אן וי- בראק קפיטל פרופרטיז אן וי",
          1121607,
          "TASE",
          "",
          34250659,
          "נדל\"ן ובינוי",
          "שקל חדש",
          27.18,
          40040.0,
          0.0,
          10.882872,
          0.0,
          0.11,
          0.06
        ],
        [
          "מגדלי ים התיכון- מגדלי הים התיכון",
          1131523,
          "TASE",
          "",
          514833888,
          "נדל\"ן ובינוי",
          "שקל חדש",
          5652.0,
          656.9,
          0.0,
          37.127988,
          0.0,
          0.36,
          0.21
        ],
        [
          "סאמיט- סאמיט",
          1081686,
          "TASE",
          "",
          520043720,
          "נדל\"ן ובינוי",
          "שקל חדש",
          1350.0,
          3106.0,
          0.0,
          41.931,
          0.0,
          0.41,
          0.24
        ],
        [
          "אנרג'יקס- אנרג'יקס",
          1123355,
          "TASE",
          "",
          513901371,
          "קלינטק",
          "שקל חדש",
          25031.0,
          381.9,
          0.0,
          95.593389,
          0.01,
          0.93,
          0.55
        ],
        [
          "חילן טק- חילן טק",
          1084698,
          "TASE",
          "",
          520039942,
          "שירותים",
          "שקל חדש",
          342.0,
          8044.0,
          0.0,
          27.51048,
          0.0,
          0.27,
          0.16
        ],
        [
          "בי קומיוניקיישנס- בי.קומיוניקיישנס",
          1107663,
          "TASE",
          "",
          512832742,
          "תקשורת ומדיה",
          "שקל חדש",
          939.0,
          3350.0,
          0.0,
          31.4565,
          0.0,
          0.31,
          0.18
        ],
        [
          "מטריקס- מטריקס",
          445015,
          "TASE",
          "",
          520039413,
          "תקשורת ומדיה",
          "שקל חדש",
          1846.0,
          3895.0,
          0.0,
          71.9017,
          0.0,
          0.7,
          0.42
        ],
        [
          "קנון- קנון",
          1134139,
          "TASE",
          "",
          510708480,
          "תקשורת ומדיה",
          "שקל חדש",
          449.0,
          5549.0,
          0.0,
          24.91501,
          0.0,
          0.24,
          0.14
        ],
        [
          "עדיקה סטייל- עדיקה סטייל בע\"מ",
          1143643,
          "TASE",
          "",
          514659614,
          "אופנה והלבשה",
          "שקל חדש",
          8100.0,
          746.8,
          0.0,
          60.4908,
          0.04,
          0.59,
          0.35
        ],
        [
          "אלוט תקשורת- אלוט",
          1099654,
          "TASE",
          "",
          512394776,
          "השקעות בהיי-טק",
          "שקל חדש",
          984.0,
          1936.0,
          0.0,
          19.05024,
          0.0,
          0.19,
          0.11
        ],
        [
          "ברם תעשיות- ברם תעשיות",
          1094515,
          "TASE",
          "",
          513579482,
          "כימיה, גומי ופלסטיק",
          "שקל חדש",
          2720.0,
          348.3,
          0.0,
          9.47376,
          0.01,
          0.09,
          0.05
        ],
        [
          "על בד- על בד",
          625012,
          "TASE",
          "",
          520040205,
          "כימיה, גומי ופלסטיק",
          "שקל חדש",
          0.690000000000027,
          4412.000000000001,
          0.0,
          0.0304428000000012,
          0.0,
          0.0,
          0.0
        ],
        [
          "פולירם- פולירם",
          1090943,
          "TASE",
          "",
          512776964,
          "כימיה, גומי ופלסטיק",
          "שקל חדש",
          3849.0,
          1429.0,
          0.0,
          55.00221,
          0.02,
          0.53,
          0.32
        ],
        [
          "אוברסיז קומרס בע''מ- אוברסיז קומרס בע\"מ",
          1139617,
          "TASE",
          "",
          510490071,
          "מסחר",
          "שקל חדש",
          4931.0,
          529.0,
          0.0,
          26.08499,
          0.01,
          0.25,
          0.15
        ],
        [
          "טיב טעם- טיב טעם",
          103010,
          "TASE",
          "",
          520041187,
          "מסחר",
          "שקל חדש",
          14297.0,
          258.6,
          0.0,
          36.972042,
          0.01,
          0.36,
          0.21
        ],
        [
          "4449211 מנדלסון- מנדלסון תשתיות ותעשיות בע\"מ",
          1129444,
          "TASE",
          "",
          513660373,
          "מסחר",
          "שקל חדש",
          4546.0,
          1031.0,
          0.0,
          46.86926,
          0.01,
          0.46,
          0.27
        ],
        [
          "אאורה- אאורה",
          373019,
          "TASE",
          "",
          520038274,
          "נדל\"ן ובינוי",
          "שקל חדש",
          6101.0,
          221.5,
          0.0,
          13.513715,
          0.0,
          0.13,
          0.08
        ],
        [
          "איידיאו- איידיאו גרופ",
          505016,
          "TASE",
          "",
          520039066,
          "נדל\"ן ובינוי",
          "שקל חדש",
          1310.0,
          7325.0,
          0.0,
          95.9575,
          0.0,
          0.93,
          0.55
        ],
        [
          "חג'ג' נדל''ן- קבוצת חג'ג' ייזום נדל\"ן בע\"מ",
          823013,
          "TASE",
          "",
          520033309,
          "נדל\"ן ובינוי",
          "שקל חדש",
          1695.0,
          897.6,
          0.0,
          15.21432,
          0.0,
          0.15,
          0.09
        ],
        [
          "שניב- שניב",
          1080837,
          "TASE",
          "",
          520041732,
          "עץ, נייר ודפוס",
          "שקל חדש",
          3482.0,
          342.7032489948306,
          0.11313,
          11.93292713,
          0.01,
          0.12,
          0.07
        ],
        [
          "או.פי.סי אנרגיה בע\"מ- או.פי.סי אנרגיה בע\"מ",
          1141571,
          "TASE",
          "",
          514401702,
          "קלינטק",
          "שקל חדש",
          1900.0,
          1848.0,
          0.0,
          35.112,
          0.0,
          0.34,
          0.2
        ],
        [
          "אל על- אל על",
          1087824,
          "TASE",
          "",
          520017146,
          "שירותים",
          "שקל חדש",
          14110.0,
          77.8,
          0.0,
          10.97758,
          0.0,
          0.11,
          0.06
        ],
        [
          "פוינטר",
          1138189,
          "TASE",
          "",
          520041476,
          "שירותים",
          "שקל חדש",
          1496.0,
          4379.0,
          0.0,
          65.50984,
          0.02,
          0.64,
          0.38
        ],
        [
          "BAGR LN- BAGIR GROUP LTD",
          "IL0011317216",
          "LSE",
          "בלומברג",
          "",
          "Consumer Durables & Apparel",
          "לירה שטרלינג",
          67000.0,
          1.75,
          0.0,
          5.63679375,
          0.02,
          0.05,
          0.03
        ],
        [
          "PNTR US- פוינטר",
          "IL0010826274",
          "NASDAQ",
          "בלומברג",
          520041476,
          "Consumer Durables & Apparel",
          "דולר אמריקאי",
          700.0,
          1200.0,
          0.0,
          30.66,
          0.01,
          0.3,
          0.18
        ],
        [
          "BAC US- BANK OF AMERICA",
          "US0605051046",
          "NYSE",
          "בלומברג",
          "",
          "Banks",
          "דולר אמריקאי",
          2330.0,
          2819.0,
          0.0,
          239.741855,
          0.0,
          2.33,
          1.38
        ],
        [
          "C US- CITIGROUP",
          "US1729674242",
          "אחר",
          "בלומברג",
          "",
          "Banks",
          "דולר אמריקאי",
          1440.0,
          6692.0,
          0.0,
          351.73152,
          0.0,
          3.42,
          2.03
        ],
        [
          "MUV2 GY- MUNICH RE",
          "DE0008430026",
          "אחר",
          "בלומברג",
          "",
          "Banks",
          "אירו",
          195.0,
          18105.0,
          0.0,
          150.225241725,
          0.0,
          1.46,
          0.87
        ],
        [
          "RF US(דיבידנד לקבל)- Regions Financial Corp",
          "US7591EP1005",
          "NYSE",
          "בלומברג",
          "",
          "Banks",
          "דולר אמריקאי",
          0.0,
          0.0,
          0.0,
          0.3695625,
          0.0,
          0.0,
          0.0
        ],
        [
          "DG US- DOLLAR GENERAL CORP",
          "US2566771059",
          "NYSE",
          "בלומברג",
          "",
          "Consumer Durables & Apparel",
          "דולר אמריקאי",
          315.0,
          9860.0,
          0.0,
          113.36535,
          0.0,
          1.1,
          0.65
        ],
        [
          "F US- Ford Motor Co",
          "US3453708600",
          "NYSE",
          "בלומברג",
          "",
          "Consumer Durables & Apparel",
          "דולר אמריקאי",
          5560.0,
          1107.0,
          0.0,
          224.65458,
          0.0,
          2.18,
          1.3
        ],
        [
          "VOW3 GY- VOLKSWAGEN",
          "DE0007664039",
          "אחר",
          "בלומברג",
          "",
          "Consumer Durables & Apparel",
          "אירו",
          210.0,
          14222.0,
          0.0,
          127.08366762,
          0.0,
          1.23,
          0.73
        ],
        [
          "RDS/A US- ROYAL DUTCH",
          "US7802592060",
          "NYSE",
          "בלומברג",
          "",
          "Energy",
          "דולר אמריקאי",
          200.0,
          6923.0,
          0.0,
          50.5379,
          0.0,
          0.49,
          0.29
        ],
        [
          "TOT US- TOTAL SA",
          "US89151E1091",
          "NYSE",
          "בלומברג",
          "",
          "Energy",
          "דולר אמריקאי",
          900.0,
          6056.0,
          0.5597275,
          199.4993275,
          0.0,
          1.94,
          1.15
        ],
        [
          "GILD US- GILEAD",
          "US3755581036",
          "NASDAQ",
          "בלומברג",
          "",
          "Pharmaceuticals & Biotechnology",
          "דולר אמריקאי",
          750.0,
          7084.0,
          0.0,
          193.9245,
          0.0,
          1.88,
          1.12
        ],
        [
          "GOOGL US- alphabet",
          "US02079K3059",
          "NASDAQ",
          "בלומברג",
          "",
          "Software & Services",
          "דולר אמריקאי",
          14.0,
          112919.0,
          0.0,
          57.701609,
          0.0,
          0.56,
          0.33
        ],
        [
          "CSCO US- CISCO",
          "US17275R1023",
          "NASDAQ",
          "בלומברג",
          "",
          "Software & Services",
          "דולר אמריקאי",
          2400.0,
          4303.0,
          0.0,
          376.9428,
          0.0,
          3.66,
          2.18
        ],
        [
          "FB US- FACEBOOK",
          "US30303M1027",
          "NASDAQ",
          "בלומברג",
          "",
          "Software & Services",
          "דולר אמריקאי",
          -80.0,
          19432.0,
          0.0,
          -56.74144,
          0.0,
          -0.55,
          -0.33
        ],
        [
          "ORCL US- ORACLE",
          "US68389X1054",
          "NYSE",
          "בלומברג",
          "",
          "Software & Services",
          "דולר אמריקאי",
          1860.0,
          4406.0,
          0.0,
          299.12334,
          0.0,
          2.91,
          1.73
        ],
        [
          "SMSN LI- SAMSUNG",
          "US7960508882",
          "אחר",
          "בלומברג",
          "",
          "Software & Services",
          "דולר אמריקאי",
          20.0,
          104500.0,
          0.0,
          76.285,
          0.0,
          0.74,
          0.44
        ],
        [
          "V US- visa",
          "US92826C8394",
          "NYSE",
          "בלומברג",
          "",
          "Software & Services",
          "דולר אמריקאי",
          315.0,
          13245.0,
          0.0,
          152.2843875,
          0.0,
          1.48,
          0.88
        ],
        [
          "ARNC US- Arconic Inc",
          "US03965L1008",
          "NYSE",
          "בלומברג",
          "",
          "Technology Hardware & Equipment",
          "דולר אמריקאי",
          2330.0,
          1701.0,
          0.0,
          144.661545,
          0.0,
          1.41,
          0.83
        ],
        [
          "CMI US- CUMMINGS",
          "US2310211063",
          "אחר",
          "בלומברג",
          "",
          "Technology Hardware & Equipment",
          "דולר אמריקאי",
          210.0,
          13300.0,
          0.0,
          101.9445,
          0.0,
          0.99,
          0.59
        ],
        [
          "LRCX US- LAM RESEARCH",
          "US5128071082",
          "NASDAQ",
          "בלומברג",
          "",
          "Technology Hardware & Equipment",
          "דולר אמריקאי",
          240.0,
          17285.0,
          0.0,
          151.4166,
          0.0,
          1.47,
          0.87
        ],
        [
          "UPS US(דיבידנד לקבל)- UNITED PARCEL SERVICES",
          "US9113121068",
          "NYSE",
          "בלומברג",
          "",
          "Technology Hardware & Equipment",
          "דולר אמריקאי",
          0.0,
          0.0,
          0.0,
          0.215861,
          0.0,
          0.0,
          0.0
        ],
        [
          "T US- AT & T CORP",
          "US00206R1023",
          "NYSE",
          "בלומברג",
          "",
          "ציוד תקשורת",
          "דולר אמריקאי",
          650.0,
          3211.0,
          0.0,
          76.180975,
          0.0,
          0.74,
          0.44
        ]
      ]
    },
    "תעודות סל": {
      "columns": [
        "שם המנפיק/שם נייר ערך",
        "מספר ני\"ע",
        "זירת מסחר",
        "מספר מנפיק",
        "ענף מסחר",
        "סוג מטבע",
        "ערך נקוב",
        "שער",
        "פדיון/ ריבית לקבל",
        "שווי שוק",
        "שעור מערך נקוב מונפק",
        "שעור מנכסי אפיק ההשקעה",
        "שעור מסך נכסי השקעה"
      ],
      "data": [
        [
          "פסגות סל בנקים- פסגות סל",
          1104645,
          "TASE",
          512894510,
          "בנקים",
          "שקל חדש",
          29130,
          1915,
          0.0,
          557.8395,
          0.02,
          10.77,
          3.22
        ],
        [
          "הראל סל MSCI שווקים מתעוררים- הראל סל בע\"מ",
          1132596,
          "TASE",
          514103811,
          "מניות",
          "שקל חדש",
          15460,
          3984,
          0.0,
          615.9264,
          0.27,
          11.89,
          3.56
        ],
        [
          "*S&P500 קסם- קסם תעודות סל",
          1117324,
          "TASE",
          513943019,
          "מניות",
          "שקל חדש",
          5000,
          10170,
          0.0,
          508.5,
          0.01,
          9.81,
          2.94
        ],
        [
          "תכלית ארה''ב S&P IXMNTR - תכלית תעודות סל",
          1136944,
          "TASE",
          513594101,
          "מניות",
          "שקל חדש",
          6100,
          7946,
          0.0,
          484.706,
          0.08,
          9.35,
          2.8
        ],
        [
          "IGV US- iShares",
          "US4642875151",
          "NYSE",
          "",
          "Technology Hardware & Equipment",
          "דולר אמריקאי",
          250,
          18268,
          0.026061,
          166.721561,
          0.0,
          3.22,
          0.96
        ],
        [
          "XLI US- SPDR",
          "US81369Y7040",
          "NYSE",
          "",
          "Technology Hardware & Equipment",
          "דולר אמריקאי",
          260,
          7163,
          0.0,
          67.97687,
          0.0,
          1.31,
          0.39
        ],
        [
          "ITA US- iShares",
          "us4642887602",
          "אחר",
          "",
          "אחר",
          "דולר אמריקאי",
          290,
          19247,
          0.3447425,
          204.0742375,
          0.0,
          3.94,
          1.18
        ],
        [
          "GNR US- SPDR",
          "US78463X5418",
          "NYSE",
          "",
          "אחר",
          "דולר אמריקאי",
          400,
          5008,
          0.0,
          73.1168,
          0.0,
          1.41,
          0.42
        ],
        [
          "XLP US- SPDR",
          "US81369Y308",
          "NYSE",
          "",
          "אחר",
          "דולר אמריקאי",
          530,
          5153,
          0.0,
          99.684785,
          0.0,
          1.92,
          0.58
        ],
        [
          "אנרגיה - XLE- SPDR",
          "US81369Y5069",
          "אחר",
          "",
          "אחר",
          "דולר אמריקאי",
          800,
          7594,
          0.0,
          221.7448,
          0.0,
          4.28,
          1.28
        ],
        [
          "DXJS US- WISDOMTREE",
          "US97717W5215",
          "NASDAQ",
          "",
          "אחר",
          "דולר אמריקאי",
          600,
          4361,
          0.0,
          95.5059,
          0.02,
          1.84,
          0.55
        ],
        [
          "IWN US- קרנות השקעה",
          "US4642876308",
          "אחר",
          "",
          "אחר",
          "דולר אמריקאי",
          300,
          13192,
          0.0,
          144.4524,
          0.0,
          2.79,
          0.83
        ],
        [
          "סמיקונד הולדרס- Merrill Lynch",
          "US8166362033",
          "אחר",
          "",
          "השקעות בהיי-טק",
          "דולר אמריקאי",
          150,
          10267,
          0.0,
          56.211825,
          0.0,
          1.08,
          0.32
        ],
        [
          "IWDA LN- iShares",
          "IE00B4L5Y983",
          "אחר",
          "",
          "מניות",
          "דולר אמריקאי",
          395,
          5465,
          0.0,
          78.7916375,
          0.0,
          1.52,
          0.45
        ],
        [
          "SPLV US- POWERSHARES",
          "US73937B7799",
          "NYSE",
          "",
          "מניות",
          "דולר אמריקאי",
          2000,
          4741,
          0.0,
          346.093,
          0.0,
          6.68,
          2.0
        ],
        [
          "SDJ600 GY- SOURCE INVESTMENT",
          "IE00B60SWW18",
          "אחר",
          "",
          "מניות",
          "אירו",
          2250,
          7890,
          0.0,
          755.3866275,
          0.05,
          14.58,
          4.36
        ],
        [
          "KBE US- SPDR",
          "US78464A7972",
          "אחר",
          "",
          "מניות",
          "דולר אמריקאי",
          1020,
          4716,
          0.0,
          175.57668,
          0.0,
          3.39,
          1.01
        ],
        [
          "XLF US- SPDR",
          "US81369Y6059",
          "NYSE",
          "",
          "מניות",
          "דולר אמריקאי",
          2000,
          2659,
          0.0,
          194.107,
          0.0,
          3.75,
          1.12
        ],
        [
          "DXJ US- WISDOMTREE",
          "US97717W8516",
          "NYSE",
          "",
          "מניות",
          "דולר אמריקאי",
          1700,
          5398,
          0.0,
          334.9459,
          0.0,
          6.46,
          1.93
        ]
      ]
    },
    "השקעות אחרות ": {
      "columns": [
        "שם המנפיק/שם נייר ערך",
        "מספר ני\"ע",
        "דירוג",
        "שם המדרג",
        "שעור הריבית",
        "סוג מטבע",
        "תשואה לפדיון",
        "שווי הוגן",
        "שעור מנכסי אפיק ההשקעה",
        "שעור מסך נכסי השקעה"
      ],
      "data": [
        [
          "BAC US(דיבידנד לקבל)",
          703831380,
          0,
          "S&P",
          0,
          "דולר אמריקאי",
          0,
          0.612324,
          56.8,
          0
        ],
        [
          "SMSN LI(דיבידנד לקבל)",
          706327320,
          0,
          "לא מדורג",
          0,
          "דולר אמריקאי",
          0,
          0.465667,
          43.2,
          0
        ]
      ]
    }
  }
}