{
  "info": {
    "key": "g472_0218"
  },
  "sheets": {
    "מזומנים": {
      "columns": [
        "שם המנפיק/שם נייר ערך",
        "מספר ני\"ע",
        "מספר מנפיק",
        "דירוג",
        "שם מדרג",
        "סוג מטבע",
        "שיעור ריבית",
        "תשואה לפידיון",
        "שווי שוק",
        "שעור מנכסי אפיק ההשקעה",
        "שעור מסך נכסי השקעה"
      ],
      "data": [
        [
          "עו'ש- לאומי",
          "1111111111- 10- לאומי",
          10,
          "AAA.IL",
          "S&P מעלות",
          "שקל חדש",
          0,
          0,
          26438.29462,
          94.25,
          6.87
        ],
        [
          "$ אוסטרלי- לאומי",
          "130018- 10- לאומי",
          10,
          "AAA.IL",
          "S&P מעלות",
          "דולר אוסטרלי",
          0,
          0,
          0.00040191,
          0.0,
          0.0
        ],
        [
          "דולר- לאומי",
          "20001- 10- לאומי",
          10,
          "AAA.IL",
          "S&P מעלות",
          "דולר אמריקאי",
          0,
          0,
          924.08615183,
          3.29,
          0.24
        ],
        [
          "דולר- לאומי",
          "20001- 10- לאומי",
          10,
          "AAA.IL",
          "S&P מעלות",
          "דולר אמריקאי",
          0,
          0,
          0.72881477,
          0.0,
          0.0
        ],
        [
          "יורו- לאומי",
          "20003- 10- לאומי",
          10,
          "AAA.IL",
          "S&P מעלות",
          "אירו",
          0,
          0,
          -557.10939945,
          -1.99,
          -0.14
        ],
        [
          "יורו(לקבל)- לאומי",
          "20003- 10- לאומי",
          10,
          "AAA.IL",
          "S&P מעלות",
          "אירו",
          0,
          0,
          1245.262378188,
          4.44,
          0.32
        ],
        [
          "לי\"ש- לאומי",
          "70002- 10- לאומי",
          10,
          "AAA.IL",
          "S&P מעלות",
          "לירה שטרלינג",
          0,
          0,
          1.20334775,
          0.0,
          0.0
        ],
        [
          "פר\"ש- לאומי",
          "30005- 10- לאומי",
          10,
          "AAA.IL",
          "S&P מעלות",
          "פרנק שווצרי",
          0,
          0,
          0.004716885,
          0.0,
          0.0
        ]
      ]
    },
    "תעודות התחייבות ממשלתיות": {
      "columns": [
        "שם המנפיק/שם נייר ערך",
        "מספר ני\"ע",
        "זירת מסחר",
        "דירוג",
        "שם מדרג",
        "תאריך רכישה",
        "מח\"מ",
        "סוג מטבע",
        "שיעור ריבית",
        "תשואה לפידיון",
        "ערך נקוב",
        "שער",
        "פדיון/ ריבית לקבל",
        "שווי שוק",
        "שעור מערך נקוב**** מונפק",
        "שעור מנכסי אפיק ההשקעה",
        "שעור מסך נכסי השקעה"
      ],
      "data": [
        [
          "גליל 5904- גליל",
          9590431,
          "TASE",
          "RF",
          "",
          "07/04/16",
          5.43,
          "שקל חדש",
          4.0,
          -0.01,
          310000,
          158.29,
          0,
          490.699,
          0.0,
          0.2,
          0.13
        ],
        [
          "ממשל צמודה 0527- גליל",
          1140847,
          "TASE",
          "RF",
          "",
          "31/07/17",
          8.66,
          "שקל חדש",
          0.75,
          0.46,
          8302945,
          103.7,
          0,
          8610.153965,
          0.1,
          3.43,
          2.24
        ],
        [
          "ממשל צמודה 1025- גליל",
          1135912,
          "TASE",
          "RF",
          "",
          "26/01/16",
          7.14,
          "שקל חדש",
          0.75,
          0.22,
          69862512,
          104.89,
          0,
          73278.7888368,
          0.5,
          29.18,
          19.03
        ],
        [
          "ממשלתי צמוד 1020- גליל",
          1137181,
          "TASE",
          "RF",
          "",
          "26/04/17",
          2.33,
          "שקל חדש",
          0.1,
          -0.7,
          8523199,
          102.86,
          0,
          8766.9624914,
          0.06,
          3.49,
          2.28
        ],
        [
          "מ.ק.מ 918 פדיון 5.9.18- בנק ישראל- מק\"מ",
          8180911,
          "TASE",
          "RF",
          "",
          "05/09/17",
          0.18,
          "שקל חדש",
          0.0,
          0.06,
          6670000,
          99.99,
          0,
          6669.333,
          0.07,
          2.66,
          1.73
        ],
        [
          "מ.ק.מ. 419 פדיון 03.04.2019- בנק ישראל- מק\"מ",
          8190415,
          "TASE",
          "RF",
          "",
          "10/04/18",
          0.75,
          "שקל חדש",
          0.0,
          0.19,
          18400000,
          99.86,
          0,
          18374.24,
          0.23,
          7.32,
          4.77
        ],
        [
          "ממשל שקלית 0219- שחר",
          1110907,
          "TASE",
          "RF",
          "",
          "02/03/17",
          0.66,
          "שקל חדש",
          6.0,
          0.17,
          8172380,
          105.88,
          0,
          8652.915944,
          0.05,
          3.45,
          2.25
        ],
        [
          "ממשל שקלית 0347- שחר",
          1140193,
          "TASE",
          "RF",
          "",
          "30/10/17",
          18.45,
          "שקל חדש",
          3.75,
          3.2,
          15225566,
          111.1,
          0,
          16915.603826,
          0.25,
          6.74,
          4.39
        ],
        [
          "ממשל שקלית 0825- שחר",
          1135557,
          "TASE",
          "RF",
          "",
          "10/03/16",
          6.7,
          "שקל חדש",
          1.75,
          1.72,
          34049295,
          101.68,
          0,
          34621.323156,
          0.21,
          13.79,
          8.99
        ],
        [
          "ממשל שקלית 1018- שחר",
          1136548,
          "TASE",
          "RF",
          "",
          "24/07/16",
          0.33,
          "שקל חדש",
          0.5,
          0.09,
          28606303,
          100.47,
          0,
          28740.7526241,
          0.29,
          11.45,
          7.47
        ],
        [
          "ממשל שקלית 120- שחר",
          1115773,
          "TASE",
          "RF",
          "",
          "20/12/17",
          1.54,
          "שקל חדש",
          5.0,
          0.36,
          3100000,
          109.39,
          0,
          3391.09,
          0.02,
          1.35,
          0.88
        ],
        [
          "ממשל שקלית 519- שחר",
          1131770,
          "TASE",
          "RF",
          "",
          "17/08/17",
          0.91,
          "שקל חדש",
          2.25,
          0.19,
          8388337,
          102.07,
          0,
          8561.9755759,
          0.04,
          3.41,
          2.22
        ],
        [
          "ממשלתי שקלית 0142- שחר",
          1125400,
          "TASE",
          "RF",
          "",
          "25/01/16",
          15.18,
          "שקל חדש",
          5.5,
          2.95,
          23444168,
          145.17,
          0,
          34033.8986856,
          0.13,
          13.55,
          8.84
        ]
      ]
    },
    "אג\"ח קונצרני": {
      "columns": [
        "שם המנפיק/שם נייר ערך",
        "מספר ני\"ע",
        "זירת מסחר",
        "ספק מידע",
        "מספר מנפיק",
        "ענף מסחר",
        "דירוג",
        "שם מדרג",
        "תאריך רכישה",
        "מח\"מ",
        "סוג מטבע",
        "שיעור ריבית",
        "תשואה לפידיון",
        "ערך נקוב",
        "שער",
        "פדיון/ ריבית לקבל",
        "שווי שוק",
        "שעור מערך נקוב מונפק",
        "שעור מנכסי אפיק ההשקעה",
        "שעור מסך נכסי השקעה"
      ],
      "data": [
        [
          "לאומי אגח 177- בנק לאומי לישראל בע\"מ",
          6040315,
          "TASE",
          "אחר",
          520018078,
          "בנקים",
          "AAA.IL",
          "S&P מעלות",
          "25/01/16",
          1.99,
          "שקל חדש",
          0.59,
          -0.05,
          9646302.0,
          101.47029555160101,
          28.5098,
          9788.1311492,
          0.18,
          17.53,
          2.54
        ],
        [
          "מזרחי טפ הנפק אגח 38- מזרחי טפחות חברה להנפקות בע\"מ",
          2310142,
          "TASE",
          "אחר",
          520032046,
          "בנקים",
          "AAA.IL",
          "S&P מעלות",
          "25/01/16",
          1.69,
          "שקל חדש",
          0.41,
          0.01,
          1128704.98,
          100.7,
          0.0,
          1136.60591486,
          0.07,
          2.04,
          0.3
        ],
        [
          "מזרחי טפ הנפק אגח 39- מזרחי טפחות חברה להנפקות בע\"מ",
          2310159,
          "TASE",
          "אחר",
          520032046,
          "בנקים",
          "AAA.IL",
          "S&P מעלות",
          "10/02/16",
          1.58,
          "שקל חדש",
          0.64,
          -0.05,
          10308330.0,
          101.35,
          0.0,
          10447.492455,
          0.33,
          18.71,
          2.71
        ],
        [
          "פועלים הנ אגח 33- הפועלים הנפקות בע\"מ",
          1940568,
          "TASE",
          "אחר",
          520032640,
          "בנקים",
          "AAA.IL",
          "S&P מעלות",
          "25/01/16",
          1.2,
          "שקל חדש",
          1.6,
          -0.04,
          2367045.0,
          102.93,
          0.0,
          2436.3994185,
          0.08,
          4.36,
          0.63
        ],
        [
          "פועלים הנפקות סדרה 34- הפועלים הנפקות בע\"מ",
          1940576,
          "TASE",
          "אחר",
          520032640,
          "בנקים",
          "AAA.IL",
          "S&P מעלות",
          "26/04/16",
          2.72,
          "שקל חדש",
          0.7,
          0.09,
          4497299.56,
          103.48,
          0.0,
          4653.805584688,
          0.13,
          8.34,
          1.21
        ],
        [
          "בינלאומי הנפק ט- הבינלאומי הראשון הנפקות בע\"מ",
          1135177,
          "TASE",
          "אחר",
          513141879,
          "בנקים",
          "AA+.IL",
          "S&P מעלות",
          "26/04/16",
          1.74,
          "שקל חדש",
          0.8,
          -0.08,
          555000.0,
          103.38,
          0.0,
          573.759,
          0.09,
          1.03,
          0.15
        ],
        [
          "בינלאומי הנפקות כ נדחה- הבינלאומי הראשון הנפקות בע\"מ",
          1121953,
          "TASE",
          "אחר",
          513141879,
          "בנקים",
          "AA.IL",
          "S&P מעלות",
          "25/01/16",
          1.56,
          "שקל חדש",
          3.1,
          -0.17,
          835951.2,
          112.76,
          0.0,
          942.61857312,
          0.16,
          1.69,
          0.24
        ],
        [
          "תמר פטרוליום אגח א- תמר פטרוליום בעמ",
          1141332,
          "TASE",
          "אחר",
          515334662,
          "חיפושי נפט וגז",
          "A1.IL",
          "מידרוג",
          "19/07/17",
          5.47,
          "שקל חדש",
          4.69,
          6.21,
          902252.0,
          97.61,
          0.0,
          880.6881772,
          0.04,
          1.58,
          0.23
        ],
        [
          "TEVA 4.1 10/01/46- טבע תעשיות פרמצבטיות בע\"מ",
          "US88167AAF84",
          "אחר",
          "בלומברג",
          520013954,
          "Pharmaceuticals & Biotechnology",
          "BB",
          "S&P",
          "09/11/17",
          14.8,
          "דולר אמריקאי",
          4.1,
          6.2,
          962000.0,
          74.06366666320166,
          0.0,
          2599.8850350717,
          0.05,
          4.66,
          0.68
        ],
        [
          "BAC 3.419 12/20/28- Bank of America",
          "US06051GHD43",
          "אחר",
          "בלומברג",
          10043,
          "Banks",
          "A-",
          "S&P",
          "28/05/18",
          8.83,
          "דולר אמריקאי",
          3.42,
          4.17,
          336000.0,
          94.02897776785714,
          0.0,
          1152.8554459797,
          0.0,
          2.07,
          0.3
        ],
        [
          "BAC 4% 04/01/24- Bank of America",
          "US06051GFF19",
          "אחר",
          "בלומברג",
          10043,
          "Banks",
          "A-",
          "S&P",
          "29/03/16",
          5.17,
          "דולר אמריקאי",
          4.0,
          3.81,
          365000.0,
          102.02977778082192,
          0.0,
          1358.9193057961,
          0.01,
          2.43,
          0.35
        ],
        [
          "Bac 4.125  01/24- Bank of America",
          "US06051GFB05",
          "אחר",
          "בלומברג",
          10043,
          "Banks",
          "A3",
          "Moodys",
          "10/07/17",
          4.95,
          "דולר אמריקאי",
          4.13,
          3.81,
          17000.0,
          103.5275,
          0.0,
          64.221214075,
          0.0,
          0.12,
          0.02
        ],
        [
          "JPM 3.3 04/01/26- JP MORGAN",
          "US46625HQW33",
          "אחר",
          "בלומברג",
          10232,
          "Banks",
          "A-",
          "S&P",
          "31/01/18",
          6.84,
          "דולר אמריקאי",
          3.3,
          3.98,
          85000.0,
          96.45949317647059,
          0.0,
          299.1835870108,
          0.0,
          0.54,
          0.08
        ],
        [
          "JPM 3.9 07/15/25- JP MORGAN",
          "US46625HMN79",
          "אחר",
          "בלומברג",
          10232,
          "Banks",
          "A3",
          "Moodys",
          "16/03/16",
          6.13,
          "דולר אמריקאי",
          3.9,
          3.95,
          620000.0,
          101.63895890322581,
          0.0,
          2299.4594784348,
          0.02,
          4.12,
          0.6
        ],
        [
          "WFC 3 04/22/26- WELLS FARGO COMPANY",
          "US949746RW34",
          "אחר",
          "בלומברג",
          10486,
          "Banks",
          "A-",
          "S&P",
          "31/01/18",
          6.96,
          "דולר אמריקאי",
          3.0,
          4.11,
          93000.0,
          93.41124655913978,
          0.0,
          316.9976039857,
          0.0,
          0.57,
          0.08
        ],
        [
          "WFC 3.55 09/29/25- WELLS FARGO COMPANY",
          "US94974BGP94",
          "אחר",
          "בלומברג",
          10486,
          "Banks",
          "A-",
          "S&P",
          "16/03/16",
          6.39,
          "דולר אמריקאי",
          3.55,
          4.02,
          634000.0,
          98.14663889589906,
          0.0,
          2270.5891209994,
          0.03,
          4.07,
          0.59
        ],
        [
          "C 3.4 05/01/26- CITIGROUP INC",
          "US172967KN09",
          "אחר",
          "בלומברג",
          10083,
          "Banks",
          "BBB+",
          "S&P",
          "31/01/18",
          6.89,
          "דולר אמריקאי",
          3.4,
          4.2,
          92000.0,
          95.47795891304348,
          0.0,
          320.5271463078,
          0.0,
          0.57,
          0.08
        ],
        [
          "C 3.7 12/01/2026- CITIGROUP INC",
          "US172967KG57",
          "אחר",
          "בלומברג",
          10083,
          "Banks",
          "Baa1",
          "Moodys",
          "15/03/16",
          6.52,
          "דולר אמריקאי",
          3.7,
          4.21,
          633000.0,
          98.65111110584517,
          0.0,
          2278.6601350117,
          0.03,
          4.08,
          0.59
        ],
        [
          "Verizon 4.125% 16/03/2027- VERIZON COMMUNICATI",
          "US92343VDY74",
          "אחר",
          "בלומברג",
          10469,
          "Telecommunication Services",
          "BBB+",
          "S&P",
          "29/03/17",
          7.32,
          "דולר אמריקאי",
          4.13,
          4.33,
          420714.0,
          100.00273972342256,
          0.0,
          1535.2274458336,
          0.01,
          2.75,
          0.4
        ],
        [
          "Swk 5.75% 15.12.53- Stanley black & decker i",
          "US854502AF89",
          "אחר",
          "בלומברג",
          12716,
          "Capital Goods",
          "Baa2",
          "Moodys",
          "06/06/16",
          15.57,
          "דולר אמריקאי",
          5.75,
          5.76,
          86000.0,
          101.26263883720931,
          0.0,
          317.7763374406,
          0.02,
          0.57,
          0.08
        ],
        [
          "Wpp LN 3.75 19/09/24",
          "US92936MAF41",
          "אחר",
          "בלומברג",
          12987,
          "Media",
          "BBB",
          "S&P",
          "01/05/16",
          5.55,
          "דולר אמריקאי",
          3.75,
          4.36,
          20000.0,
          97.93625,
          0.0,
          71.47387525,
          0.0,
          0.13,
          0.02
        ],
        [
          "Grand city properties 2.5- GRAND CITY PROPERTIES",
          "XS1811181566",
          "אחר",
          "בלומברג",
          11148,
          "Real Estate",
          "BBB-",
          "S&P",
          "23/04/18",
          5.02,
          "אירו",
          2.5,
          3.34,
          248000.0,
          96.41120548387097,
          0.0,
          1010.38789089168,
          0.07,
          1.81,
          0.26
        ],
        [
          "PEMEX 4.5 01/26",
          "US71654QBW15",
          "אחר",
          "בלומברג",
          12345,
          "Energy",
          "Baa3",
          "Moodys",
          "04/04/16",
          6.33,
          "דולר אמריקאי",
          4.5,
          5.64,
          603000.0,
          95.3895,
          0.0,
          2098.900001565,
          0.04,
          3.76,
          0.55
        ],
        [
          "VW 3.75% 24/03/49- Volkswagen intl fin",
          "XS1048428012",
          "אחר",
          "בלומברג",
          16302,
          "Automobiles & Components",
          "BBB-",
          "S&P",
          "05/07/16",
          18.79,
          "אירו",
          3.75,
          3.57,
          228000.0,
          104.27830135964912,
          0.0,
          1004.70308061918,
          0.02,
          1.8,
          0.26
        ],
        [
          "Bayer 3.75% 01/07/74- Bayer AG",
          "DE000A11QR73",
          "אחר",
          "בלומברג",
          12075,
          "Pharmaceuticals & Biotechnology",
          "BB+",
          "S&P",
          "15/03/16",
          23.93,
          "אירו",
          3.75,
          3.56,
          338000.0,
          108.24863014792899,
          0.0,
          1546.13726712342,
          0.02,
          2.77,
          0.4
        ],
        [
          "Cielbz 3.75% 16/11/22- Cielo sa",
          "USP28610AA46",
          "אחר",
          "בלומברג",
          12830,
          "Commercial & Professional Services",
          "Ba1",
          "Moodys",
          "15/03/16",
          4.06,
          "דולר אמריקאי",
          3.75,
          5.56,
          447000.0,
          93.68966666666667,
          0.0,
          1528.17496369,
          0.05,
          2.74,
          0.4
        ],
        [
          "PTTEPT 4 7/8 PERP- Ptt explor & product",
          "USY7150MAB38",
          "אחר",
          "בלומברג",
          12829,
          "Energy",
          "BB+",
          "S&P",
          "02/08/17",
          0.96,
          "דולר אמריקאי",
          4.88,
          4.49,
          84000.0,
          100.53741666666667,
          0.0,
          308.16326807,
          0.02,
          0.55,
          0.08
        ],
        [
          "BRFSBZ 4 3/4 05/22/2- BRF-BRASIL FOODS SA-ADR",
          "USP1905CAE05",
          "אחר",
          "בלומברג",
          10889,
          "Food, Beverage & Tobacco",
          "Ba2",
          "Moodys",
          "16/08/16",
          5.14,
          "דולר אמריקאי",
          4.75,
          7.46,
          471000.0,
          88.289,
          0.0,
          1517.40450231,
          0.06,
          2.72,
          0.39
        ],
        [
          "Telefonica 6.5 29/09/49- TELEFONICA S.A",
          "XS0972570351",
          "אחר",
          "בלומברג",
          10414,
          "Telecommunication Services",
          "Ba2",
          "Moodys",
          "04/04/16",
          13.54,
          "אירו",
          6.5,
          6.39,
          237000.0,
          106.37672603375528,
          0.0,
          1065.37844223006,
          0.02,
          1.91,
          0.28
        ]
      ]
    },
    "מניות": {
      "columns": [
        "שם המנפיק/שם נייר ערך",
        "מספר ני\"ע",
        "זירת מסחר",
        "ספק מידע",
        "מספר מנפיק",
        "ענף מסחר",
        "סוג מטבע",
        "ערך נקוב",
        "שער",
        "פדיון/ ריבית לקבל",
        "שווי שוק",
        "שעור מערך נקוב מונפק",
        "שעור מנכסי אפיק ההשקעה",
        "שעור מסך נכסי השקעה"
      ],
      "data": [
        [
          "הראל השקעות- הראל השקעות בביטוח ושרותים פיננסים בע\"מ",
          585018,
          "TASE",
          "אחר",
          520033986,
          "ביטוח",
          "שקל חדש",
          6289,
          2741.0,
          0.0,
          172.38149,
          0.0,
          0.69,
          0.04
        ],
        [
          "דיסקונט א- בנק דיסקונט לישראל בע\"מ",
          691212,
          "TASE",
          "אחר",
          520007030,
          "בנקים",
          "שקל חדש",
          103590,
          1067.0,
          0.0,
          1105.3053,
          0.01,
          4.39,
          0.29
        ],
        [
          "פועלים- בנק הפועלים בע\"מ",
          662577,
          "TASE",
          "אחר",
          520000118,
          "בנקים",
          "שקל חדש",
          106917,
          2475.0,
          0.0,
          2646.19575,
          0.01,
          10.52,
          0.69
        ],
        [
          "לאומי- בנק לאומי לישראל בע\"מ",
          604611,
          "TASE",
          "אחר",
          520018078,
          "בנקים",
          "שקל חדש",
          134003,
          2160.0,
          0.0,
          2894.4648,
          0.01,
          11.5,
          0.75
        ],
        [
          "בינלאומי 5- הבנק הבינלאומי הראשון לישראל בע\"מ",
          593038,
          "TASE",
          "אחר",
          520029083,
          "בנקים",
          "שקל חדש",
          9036,
          7635.0,
          0.0,
          689.8986,
          0.01,
          2.74,
          0.18
        ],
        [
          "פתאל החזקות- פתאל החזקות 1998 בע\"מ",
          1143429,
          "TASE",
          "אחר",
          512607888,
          "מלונאות ותיירות",
          "שקל חדש",
          800,
          39380.0,
          0.0,
          315.04,
          0.01,
          1.25,
          0.08
        ],
        [
          "שופרסל- שופר-סל בע\"מ",
          777037,
          "TASE",
          "אחר",
          520022732,
          "מסחר",
          "שקל חדש",
          39719,
          2242.0,
          0.0,
          890.49998,
          0.02,
          3.54,
          0.23
        ],
        [
          "אלוני חץ- אלוני-חץ נכסים והשקעות בע\"מ",
          390013,
          "TASE",
          "אחר",
          520038506,
          "נדל\"ן ובינוי",
          "שקל חדש",
          31232,
          3360.0,
          0.0,
          1049.3952,
          0.02,
          4.17,
          0.27
        ],
        [
          "אמות- אמות השקעות בע\"מ",
          1097278,
          "TASE",
          "אחר",
          520026683,
          "נדל\"ן ובינוי",
          "שקל חדש",
          45394,
          1830.0,
          0.0,
          830.7102,
          0.01,
          3.3,
          0.22
        ],
        [
          "גזית גלוב- גזית-גלוב בע\"מ",
          126011,
          "TASE",
          "אחר",
          520033234,
          "נדל\"ן ובינוי",
          "שקל חדש",
          14273,
          3370.038,
          5.42374,
          481.00552374,
          0.01,
          1.91,
          0.12
        ],
        [
          "מליסרון- מליסרון בע\"מ",
          323014,
          "TASE",
          "אחר",
          520037789,
          "נדל\"ן ובינוי",
          "שקל חדש",
          4433,
          15150.0,
          0.0,
          671.5995,
          0.01,
          2.67,
          0.17
        ],
        [
          "עזריאלי קבוצה- קבוצת עזריאלי בע\"מ (לשעבר קנית מימון)",
          1119478,
          "TASE",
          "אחר",
          510960719,
          "נדל\"ן ובינוי",
          "שקל חדש",
          8790,
          18140.0,
          0.0,
          1594.506,
          0.01,
          6.34,
          0.41
        ],
        [
          "אינרום- אינרום תעשיות בנייה בע\"מ",
          1132356,
          "TASE",
          "אחר",
          515001659,
          "מתכת ומוצרי בניה",
          "שקל חדש",
          33652,
          1367.0,
          0.0,
          460.02284,
          0.03,
          1.83,
          0.12
        ],
        [
          "שפיר- שפיר הנדסה ותעשיה בע\"מ",
          1133875,
          "TASE",
          "אחר",
          514892801,
          "מתכת ומוצרי בניה",
          "שקל חדש",
          50826,
          1065.0,
          0.0,
          541.2969,
          0.01,
          2.15,
          0.14
        ],
        [
          "אשטרום נכסים- אשטרום נכסים בע\"מ",
          251017,
          "TASE",
          "אחר",
          520036617,
          "נדל\"ן ובינוי",
          "שקל חדש",
          6400,
          1604.0,
          0.0,
          102.656,
          0.01,
          0.41,
          0.03
        ],
        [
          "בראק קפיטל- בראק קפיטל פרופרטיז אן וי",
          1121607,
          "TASE",
          "אחר",
          34250659,
          "נדל\"ן ובינוי",
          "שקל חדש",
          118,
          40040.0,
          0.0,
          47.2472,
          0.0,
          0.19,
          0.01
        ],
        [
          "גב ים- חברת גב-ים לקרקעות בע\"מ",
          759019,
          "TASE",
          "אחר",
          520001736,
          "נדל\"ן ובינוי",
          "שקל חדש",
          246,
          157700.0,
          0.0,
          387.942,
          0.01,
          1.54,
          0.1
        ],
        [
          "לוינשטיין נכסים- לוינשטיין נכסים",
          1119080,
          "TASE",
          "אחר",
          511134298,
          "נדל\"ן ובינוי",
          "שקל חדש",
          3894,
          6793.0,
          0.0,
          264.51942,
          0.03,
          1.05,
          0.07
        ],
        [
          "ריט 1- ריט 1 בע\"מ",
          1098920,
          "TASE",
          "אחר",
          513821488,
          "נדל\"ן ובינוי",
          "שקל חדש",
          14933,
          1450.0,
          0.0,
          216.5285,
          0.01,
          0.86,
          0.06
        ],
        [
          "חילן טק- חילן טק בע\"מ",
          1084698,
          "TASE",
          "אחר",
          520039942,
          "שירותי מידע",
          "שקל חדש",
          2784,
          8044.0,
          0.0,
          223.94496,
          0.01,
          0.89,
          0.06
        ],
        [
          "דנאל כא- דנאל (אדיר יהושע) בע\"מ",
          314013,
          "TASE",
          "אחר",
          520037565,
          "שירותים",
          "שקל חדש",
          635,
          16160.0,
          0.0,
          102.616,
          0.01,
          0.41,
          0.03
        ],
        [
          "מיטב דש- מיטב דש השקעות בע\"מ",
          1081843,
          "TASE",
          "אחר",
          520043795,
          "שירותים פיננסיים",
          "שקל חדש",
          991,
          1078.0,
          0.0,
          10.68298,
          0.0,
          0.04,
          0.0
        ],
        [
          "נאוי- קבוצת האחים נאוי בע\"מ לשעבר גולדן אקוויטי",
          208017,
          "TASE",
          "אחר",
          520036070,
          "שירותים פיננסיים",
          "שקל חדש",
          3619,
          1836.0,
          0.0,
          66.44484,
          0.01,
          0.26,
          0.02
        ],
        [
          "בי קומיונקיישנס- בי קומיוניקיישנס בע\"מ לשעבר סמייל 012",
          1107663,
          "TASE",
          "אחר",
          512832742,
          "תקשורת ומדיה",
          "שקל חדש",
          767,
          3350.0,
          0.0,
          25.6945,
          0.0,
          0.1,
          0.01
        ],
        [
          "סנו- סנו-מפעלי ברונוס בע\"מ",
          813014,
          "TASE",
          "אחר",
          520032988,
          "כימיה, גומי ופלסטיק",
          "שקל חדש",
          113,
          18590.0,
          0.0,
          21.0067,
          0.0,
          0.08,
          0.01
        ],
        [
          "כלל משקאות- כלל תעשיות ומשקאות בע\"מ",
          1147685,
          "TASE",
          "אחר",
          515818524,
          "מזון",
          "שקל חדש",
          1320,
          4909.0,
          0.0,
          64.7988,
          0.01,
          0.26,
          0.02
        ],
        [
          "וילאר- וילאר אינטרנשיונל בע\"מ",
          416016,
          "TASE",
          "אחר",
          520038910,
          "נדל\"ן ובינוי",
          "שקל חדש",
          3648,
          9493.0,
          0.0,
          346.30464,
          0.02,
          1.38,
          0.09
        ],
        [
          "יעקובי קבוצה- קבוצת אחים יעקובי",
          1142421,
          "TASE",
          "אחר",
          514010081,
          "נדל\"ן ובינוי",
          "שקל חדש",
          27300,
          149.5,
          0.0,
          40.8135,
          0.02,
          0.16,
          0.01
        ],
        [
          "גלובל כנפיים- גלובל כנפיים ליסינג בע\"מ",
          1141316,
          "TASE",
          "אחר",
          513342444,
          "שירותים",
          "שקל חדש",
          28100,
          193.5,
          0.0,
          54.3735,
          0.02,
          0.22,
          0.01
        ],
        [
          "הולמס פלייס- הולמס פלייס אינטרנשיונל בע\"מ",
          1142587,
          "TASE",
          "אחר",
          512466723,
          "שירותים",
          "שקל חדש",
          16500,
          341.6,
          0.0,
          56.364,
          0.02,
          0.22,
          0.01
        ],
        [
          "פננטפארק- פננטפארק פלוטינג רייט קפיטל לימיטד",
          1142405,
          "TASE",
          "אחר",
          1504619,
          "שירותים פיננסיים",
          "שקל חדש",
          3173,
          4887.038056098329,
          1.20752,
          155.06571752,
          0.01,
          0.62,
          0.04
        ],
        [
          "Check Point Software- צ'ק פוינט",
          "IL0010824113",
          "NASDAQ",
          "בלומברג",
          520042821,
          "Software & Services",
          "דולר אמריקאי",
          1825,
          9863.0,
          0.0,
          656.81908775,
          0.0,
          2.61,
          0.17
        ],
        [
          "Boeing com- BOEING CO",
          "US0970231058",
          "NYSE",
          "בלומברג",
          27015,
          "Capital Goods",
          "דולר אמריקאי",
          415,
          33465.0,
          0.0,
          506.77220775,
          0.0,
          2.01,
          0.13
        ],
        [
          "Builders Firstsource Inc- Builders Firstsource",
          "US12008R1077",
          "NASDAQ",
          "בלומברג",
          "",
          "Capital Goods",
          "דולר אמריקאי",
          1669,
          1811.0,
          0.0,
          110.29317791,
          0.0,
          0.44,
          0.03
        ],
        [
          "Centene Corporation- Centene Corporation",
          "US15135B1017",
          "NYSE",
          "בלומברג",
          "",
          "Health Care Equipment & Services",
          "דולר אמריקאי",
          1038,
          12378.0,
          0.0,
          468.83680236,
          0.0,
          1.86,
          0.12
        ],
        [
          "Holdings plc 888- 888 Holdings plc",
          "GI000A0F6407",
          "LSE",
          "בלומברג",
          12083,
          "Hotels Restaurants & Leisure",
          "לירה שטרלינג",
          19240,
          268.8,
          0.0,
          246.949248,
          0.01,
          0.98,
          0.06
        ],
        [
          "Elxx PHARMA INC- Eloxx Pharmaceuticals Inc",
          "US29014R1032",
          "NASDAQ",
          "בלומברג",
          "",
          "Pharmaceuticals & Biotechnology",
          "דולר אמריקאי",
          1680,
          1833.0,
          0.0,
          112.3687656,
          0.01,
          0.45,
          0.03
        ],
        [
          "AROUNDTOWN SA- Aroundtown property",
          "LU1673108939",
          "FWB",
          "בלומברג",
          12853,
          "Real Estate",
          "אירו",
          14047,
          691.5,
          0.0,
          410.473104129,
          0.0,
          1.63,
          0.11
        ],
        [
          "Atrium european real estaste- Atrium european real estaste",
          "JE00B3DCF752",
          "אחר",
          "בלומברג",
          10702,
          "Real Estate",
          "אירו",
          15884,
          377.0,
          0.0,
          253.052229144,
          0.0,
          1.01,
          0.07
        ],
        [
          "Globalworth Real estate- Global worth real estate invest",
          "GG00B979FD04",
          "LSE",
          "בלומברג",
          12682,
          "Real Estate",
          "אירו",
          13521,
          940.0,
          0.0,
          537.08819292,
          0.01,
          2.13,
          0.14
        ],
        [
          "Nvidia crop- NVIDIA CORP",
          "US67066G1040",
          "NASDAQ",
          "בלומברג",
          10322,
          "Semiconductors & Semiconductor Equipment",
          "דולר אמריקאי",
          436,
          24086.0,
          0.0,
          383.19958904,
          0.0,
          1.52,
          0.1
        ],
        [
          "Alibaba Group ho- ALIBABA COM LTD",
          "US01609W1027",
          "NYSE",
          "בלומברג",
          10825,
          "Software & Services",
          "דולר אמריקאי",
          1227,
          18838.0,
          0.0,
          843.43810674,
          0.0,
          3.35,
          0.22
        ],
        [
          "BAIDU.COM ADR- Baidu.com, Inc",
          "US0567521085",
          "NASDAQ",
          "בלומברג",
          10041,
          "Software & Services",
          "דולר אמריקאי",
          915,
          24221.0,
          0.0,
          808.69922535,
          0.0,
          3.21,
          0.21
        ],
        [
          "Fortinet Inc- Fortinet Inc",
          "US34959E1091",
          "NASDAQ",
          "בלומברג",
          "",
          "Software & Services",
          "דולר אמריקאי",
          1825,
          6245.0,
          0.0,
          415.88109125,
          0.0,
          1.65,
          0.11
        ],
        [
          "Palo alto networks- Palo alto networks inc",
          "us6974351057",
          "NYSE",
          "בלומברג",
          12997,
          "Software & Services",
          "דולר אמריקאי",
          527,
          20492.0,
          0.0,
          394.06587316,
          0.0,
          1.57,
          0.1
        ],
        [
          "Tencent holdings- Tencent holdings",
          "KYG875721634",
          "HKSE",
          "בלומברג",
          11074,
          "Software & Services",
          "דולר הונג קונג",
          4323,
          37900.0,
          0.0,
          761.3723799,
          0.0,
          3.03,
          0.2
        ],
        [
          "Samsung electronics- Samsung Electronics co ltd",
          "US7960508882",
          "LSE",
          "בלומברג",
          11111,
          "Technology Hardware & Equipment",
          "דולר אמריקאי",
          206,
          103000.0,
          0.0,
          774.24482,
          0.0,
          3.08,
          0.2
        ],
        [
          "Sunny Optical- Sunny Optical Technology Group Co",
          "KYG8586D1097",
          "אחר",
          "בלומברג",
          "",
          "Technology Hardware & Equipment",
          "דולר הונג קונג",
          6778,
          13910.0,
          0.0,
          438.12836106,
          0.0,
          1.74,
          0.11
        ],
        [
          "Delta Airlines inc- Delta Air Lines, Inc",
          "US2473617023",
          "NYSE",
          "בלומברג",
          27175,
          "Transportation",
          "דולר אמריקאי",
          1361,
          4980.0,
          0.0,
          247.3211922,
          0.0,
          0.98,
          0.06
        ],
        [
          "Southwest Airlines- SOUTHWEST AIRLINES CO",
          "US8447411088",
          "NYSE",
          "בלומברג",
          10793,
          "Transportation",
          "דולר אמריקאי",
          1430,
          5070.0,
          0.0,
          264.556149,
          0.0,
          1.05,
          0.07
        ]
      ]
    },
    "תעודות סל": {
      "columns": [
        "שם המנפיק/שם נייר ערך",
        "מספר ני\"ע",
        "זירת מסחר",
        "מספר מנפיק",
        "ענף מסחר",
        "סוג מטבע",
        "ערך נקוב",
        "שער",
        "פדיון/ ריבית לקבל",
        "שווי שוק",
        "שעור מערך נקוב מונפק",
        "שעור מנכסי אפיק ההשקעה",
        "שעור מסך נכסי השקעה"
      ],
      "data": [
        [
          "Invesco QQQ  trust NAS1- Invesco",
          "US46090E1038",
          "אחר",
          21100,
          "מניות",
          "דולר אמריקאי",
          280,
          17119,
          0,
          174.9082468,
          0.0,
          11.89,
          0.05
        ],
        [
          "Ishares m .hong kong- ISHARES M.HONG KONG",
          "US4642868719",
          "NYSE",
          20056,
          "מניות",
          "דולר אמריקאי",
          7040,
          2420,
          0,
          621.672832,
          0.01,
          42.25,
          0.16
        ],
        [
          "Ishares mcsi australia- ISHARES MSCI AUSTRALIA",
          "us4642861037",
          "NYSE",
          20064,
          "מניות",
          "דולר אמריקאי",
          5090,
          2249,
          0,
          417.7159909,
          0.0,
          28.39,
          0.11
        ],
        [
          "Spdr s&p 500 etf trust- SPDR - State Street Global Advisors",
          "US78462F1030",
          "NYSE",
          22040,
          "מניות",
          "דולר אמריקאי",
          260,
          27089,
          0,
          257.0041786,
          0.0,
          17.47,
          0.07
        ]
      ]
    },
    "קרנות נאמנות": {
      "columns": [
        "שם המנפיק/שם נייר ערך",
        "מספר ני\"ע",
        "זירת מסחר",
        "מספר מנפיק",
        "ענף מסחר",
        "דירוג",
        "שם מדרג",
        "סוג מטבע",
        "ערך נקוב",
        "שער",
        "שווי שוק",
        "שעור מערך נקוב מונפק",
        "שעור מנכסי אפיק ההשקעה",
        "שעור מסך נכסי השקעה"
      ],
      "data": [
        [
          "*אלטשולר יתר 40 דיב ק.נ- אלטשולר שחם בית השקעות בע\"מ",
          5105903,
          "TASE",
          513862581,
          "מניות",
          0,
          "לא מדורג",
          "שקל חדש",
          20946.0,
          353.48,
          74.0399208,
          0.02,
          1.71,
          0.02
        ],
        [
          "Angsana Bond Fund- Nutrimenta Singapore pte ltd",
          "IE00BNN82M77",
          "אחר",
          12789,
          "אג\"ח",
          0,
          "לא מדורג",
          "דולר אמריקאי",
          1504.59,
          14566.0,
          799.7096562306,
          0.17,
          18.5,
          0.21
        ],
        [
          "EDR fund emerging bonds- Edmond De Rothschild",
          "lu1160351620",
          "אחר",
          513872440,
          "אג\"ח",
          0,
          "לא מדורג",
          "דולר אמריקאי",
          2349.0,
          11799.0,
          1011.35140299,
          0.11,
          23.4,
          0.26
        ],
        [
          "$Gemway -Gemequity-S- Gemequity",
          "FR0013246444",
          "אחר",
          12715,
          "מניות",
          0,
          "לא מדורג",
          "דולר אמריקאי",
          108.0,
          119869.0,
          472.39413948,
          0.03,
          10.93,
          0.12
        ],
        [
          "Comgest Growth euro- Comgest",
          "ie00bhwqnn83",
          "אחר",
          12656,
          "מניות",
          0,
          "לא מדורג",
          "אירו",
          3120.0,
          3821.0,
          503.77959216,
          0.03,
          11.65,
          0.13
        ],
        [
          "EDG-US L G-I$D- Edgewood L select",
          "LU0952587862",
          "אחר",
          13050,
          "מניות",
          0,
          "לא מדורג",
          "דולר אמריקאי",
          808.0,
          22600.0,
          666.336592,
          0.0,
          15.42,
          0.17
        ],
        [
          "Hbm Healthcare- HBM Healthcare Investment ag",
          "CH0012627250",
          "אחר",
          13052,
          "מניות",
          0,
          "לא מדורג",
          "פרנק שווצרי",
          288.0,
          15820.0,
          166.5959904,
          0.0,
          3.85,
          0.04
        ],
        [
          "KOT זמני- Kotak",
          "LU0675383409",
          "אחר",
          12688,
          "מניות",
          0,
          "לא מדורג",
          "דולר אמריקאי",
          615.0,
          1624.8,
          36.46270548,
          0.0,
          0.84,
          0.01
        ],
        [
          "KOT-IND MID-J- Kotak",
          "LU0675383409",
          "אחר",
          12688,
          "מניות",
          0,
          "לא מדורג",
          "דולר אמריקאי",
          9982.22,
          1624.8,
          591.83536243344,
          0.03,
          13.69,
          0.15
        ]
      ]
    },
    "אופציות": {
      "columns": [
        "שם המנפיק/שם נייר ערך",
        "מספר ני\"ע",
        "זירת מסחר",
        "ענף מסחר",
        "סוג מטבע",
        "ערך נקוב",
        "שער",
        "שווי שוק",
        "שעור מערך נקוב מונפק",
        "שעור מנכסי אפיק ההשקעה",
        "שעור מסך נכסי השקעה"
      ],
      "data": [
        [
          "DAX C12500 17/08/18- dax",
          70295480,
          "אחר",
          "Other",
          "אירו",
          20,
          71500.0,
          60.42894,
          0,
          -10.62,
          0.02
        ],
        [
          "DAX C12500 20/07/18- dax",
          70785258,
          "אחר",
          "Other",
          "אירו",
          10,
          31950.0,
          13.501431,
          0,
          -2.37,
          0.0
        ],
        [
          "DAX C12750 17/08/18- dax",
          70296173,
          "אחר",
          "Other",
          "אירו",
          -30,
          33050.0,
          -41.898807,
          0,
          7.37,
          -0.01
        ],
        [
          "DAX C12750 20/07/18- dax",
          70785274,
          "אחר",
          "Other",
          "אירו",
          -15,
          8800.0,
          -5.578056,
          0,
          0.98,
          0.0
        ],
        [
          "DAX P12300 17/08/18- dax",
          70283965,
          "אחר",
          "Other",
          "אירו",
          -5,
          190550.0,
          -40.2613095,
          0,
          7.08,
          -0.01
        ],
        [
          "DAX P12300 20/07/18- dax",
          70785241,
          "אחר",
          "Other",
          "אירו",
          -5,
          141800.0,
          -29.960922,
          0,
          5.27,
          -0.01
        ],
        [
          "SCM8C2720- חוזים עתידיים בחול",
          29992998,
          "אחר",
          "Other",
          "דולר אמריקאי",
          -11,
          46250.0,
          -18.5642875,
          0,
          3.26,
          0.0
        ],
        [
          "SCM8C2780- חוזים עתידיים בחול",
          29993130,
          "אחר",
          "Other",
          "דולר אמריקאי",
          11,
          250.0,
          0.1003475,
          0,
          -0.02,
          0.0
        ],
        [
          "SCM8C2820- חוזים עתידיים בחול",
          29993131,
          "אחר",
          "Other",
          "דולר אמריקאי",
          11,
          250.0,
          0.1003475,
          0,
          -0.02,
          0.0
        ],
        [
          "SCM8C2840- חוזים עתידיים בחול",
          29993139,
          "אחר",
          "Other",
          "דולר אמריקאי",
          -33,
          250.0,
          -0.3010425,
          0,
          0.05,
          0.0
        ],
        [
          "SCM8P2590- חוזים עתידיים בחול",
          29993132,
          "אחר",
          "Other",
          "דולר אמריקאי",
          22,
          500.0,
          0.40139,
          0,
          -0.07,
          0.0
        ],
        [
          "SCM8P2720- חוזים עתידיים בחול",
          29992999,
          "אחר",
          "Other",
          "דולר אמריקאי",
          11,
          48750.0,
          19.5677625,
          0,
          -3.44,
          0.01
        ],
        [
          "SCM8P2780- חוזים עתידיים בחול",
          29993140,
          "אחר",
          "Other",
          "דולר אמריקאי",
          -11,
          302500.0,
          -121.420475,
          0,
          21.34,
          -0.03
        ],
        [
          "SCN8C2720- חוזים עתידיים בחול",
          29993148,
          "אחר",
          "Other",
          "דולר אמריקאי",
          -11,
          206250.0,
          -82.7866875,
          0,
          14.55,
          -0.02
        ],
        [
          "SCN8C2800- חוזים עתידיים בחול",
          29993133,
          "אחר",
          "Other",
          "דולר אמריקאי",
          22,
          35000.0,
          28.0973,
          0,
          -4.94,
          0.01
        ],
        [
          "SCN8C2850- חוזים עתידיים בחול",
          29993134,
          "אחר",
          "Other",
          "דולר אמריקאי",
          -22,
          6750.0,
          -5.418765,
          0,
          0.95,
          0.0
        ],
        [
          "SCN8P2590- חוזים עתידיים בחול",
          29993129,
          "אחר",
          "Other",
          "דולר אמריקאי",
          22,
          73750.0,
          59.205025,
          0,
          -10.41,
          0.02
        ],
        [
          "SCN8P2720- חוזים עתידיים בחול",
          29993149,
          "אחר",
          "Other",
          "דולר אמריקאי",
          -11,
          208750.0,
          -83.7901625,
          0,
          14.73,
          -0.02
        ],
        [
          "SCQ8C2820- חוזים עתידיים בחול",
          29993147,
          "אחר",
          "Other",
          "דולר אמריקאי",
          22,
          65000.0,
          52.1807,
          0,
          -9.17,
          0.01
        ],
        [
          "SCQ8C2870- חוזים עתידיים בחול",
          29993146,
          "אחר",
          "Other",
          "דולר אמריקאי",
          -22,
          20500.0,
          -16.45699,
          0,
          2.89,
          0.0
        ],
        [
          "SCQ8P2590- חוזים עתידיים בחול",
          29993145,
          "אחר",
          "Other",
          "דולר אמריקאי",
          22,
          146250.0,
          117.406575,
          0,
          -20.64,
          0.03
        ],
        [
          "USU8C141- חוזים עתידיים בחול",
          29992992,
          "אחר",
          "Other",
          "דולר אמריקאי",
          -23,
          432812.5,
          -363.246546875,
          0,
          63.86,
          -0.09
        ],
        [
          "USU8C146- חוזים עתידיים בחול",
          29992988,
          "אחר",
          "Other",
          "דולר אמריקאי",
          46,
          112500.0,
          188.83575,
          0,
          -33.2,
          0.05
        ],
        [
          "USU8P141- חוזים עתידיים בחול",
          29992991,
          "אחר",
          "Other",
          "דולר אמריקאי",
          46,
          37500.0,
          62.94525,
          0,
          -11.07,
          0.02
        ],
        [
          "USU8P146- חוזים עתידיים בחול",
          29992989,
          "אחר",
          "Other",
          "דולר אמריקאי",
          -46,
          215625.0,
          -361.9351875,
          0,
          63.63,
          -0.09
        ]
      ]
    },
    "חוזים עתידיים": {
      "columns": [
        "שם המנפיק/שם נייר ערך",
        "מספר ני\"ע",
        "זירת מסחר",
        "ענף מסחר",
        "סוג מטבע",
        "ערך נקוב",
        "שער",
        "שווי שוק",
        "שעור מנכסי אפיק ההשקעה",
        "שעור מסך נכסי השקעה",
        "ASX",
        "אוסטרליה",
        "בנקים וחברות אחזקה",
        "untitled1",
        "אירו"
      ],
      "data": [
        [
          "Hin8- חוזים עתידיים בחול",
          70777370,
          "אחר",
          "Other",
          "דולר הונג קונג",
          1,
          -3685000.0,
          -17.124195,
          3.04,
          0.0,
          "",
          "",
          "",
          "שירותים",
          ""
        ],
        [
          "TUU8- חוזים עתידיים בחול",
          70337522,
          "אחר",
          "Other",
          "דולר אמריקאי",
          27,
          -50001.59999999655,
          -49.2630763679966,
          8.75,
          -0.01,
          "",
          "",
          "",
          "שירותים פיננסיים",
          ""
        ],
        [
          "Usum8- חוזים עתידיים בחול",
          70846563,
          "אחר",
          "Other",
          "דולר אמריקאי",
          -83,
          97488.24216867503,
          -295.259714409001,
          52.47,
          -0.08,
          "",
          "",
          "",
          "תוכנה ואינטרנט",
          ""
        ],
        [
          "ESU8_S&P500 mini Sep18- חוזים עתידיים בחול",
          70800677,
          "אחר",
          "Other",
          "דולר אמריקאי",
          15,
          -315711.38,
          -172.804623843,
          30.71,
          -0.04,
          "",
          "",
          "",
          "תיירות ומלונות",
          ""
        ],
        [
          "Nqu8_nasdaq100 mini fut Sep18- חוזים עתידיים בחול",
          70800735,
          "אחר",
          "Other",
          "דולר אמריקאי",
          6,
          -232203.92599999817,
          -50.8387275584396,
          9.03,
          -0.01,
          "",
          "",
          "",
          "תעשייה שונות",
          ""
        ],
        [
          "Xpu8_AS51_ Fut Sep 18- חוזים עתידיים בחול",
          70864327,
          "אחר",
          "Other",
          "דולר אוסטרלי",
          2,
          421239.1425000019,
          22.5733631682901,
          -4.01,
          0.01,
          "",
          "",
          "",
          "תקשורת ומדיה",
          ""
        ]
      ]
    },
    "לא סחיר - אג\"ח קונצרני": {
      "columns": [
        "שם המנפיק/שם נייר ערך",
        "מספר ני\"ע",
        "ספק המידע",
        "מספר מנפיק",
        "ענף מסחר",
        "דירוג",
        "שם מדרג",
        "תאריך רכישה",
        "מח\"מ",
        "סוג מטבע",
        "שיעור ריבית",
        "תשואה לפידיון",
        "ערך נקוב",
        "שער",
        "שווי הוגן",
        "שעור מערך נקוב מונפק",
        "שעור מנכסי אפיק ההשקעה",
        "שעור מסך נכסי השקעה"
      ],
      "data": [
        [
          "מתם מרכז תעשיות מדע חיפה אגח א לס- מת\"ם - מרכז תעשיות מדע חיפה בע\"מ",
          1138999,
          "אחר",
          510687403,
          "נדל\"ן ובינוי",
          "Aa2.IL",
          "מידרוג",
          "16/08/16",
          5.54,
          "שקל חדש",
          3.1,
          2.64,
          819850,
          103.44,
          848.05284,
          0.23,
          15.12,
          0.22
        ],
        [
          "אליהו הנפ אגח א לס- אליהו הנפקות בע\"מ",
          1142009,
          "אחר",
          515703528,
          "ביטוח",
          "A1.IL",
          "מידרוג",
          "19/09/17",
          4.85,
          "שקל חדש",
          3.85,
          4.01,
          1596000,
          100.48,
          1603.6608,
          0.12,
          28.59,
          0.42
        ],
        [
          "ביטוח ישיר אגח יא- ביטוח ישיר - השקעות פיננסיות בע\"מ",
          1138825,
          "אחר",
          520044439,
          "השקעה ואחזקות",
          "A2.IL",
          "מידרוג",
          "21/07/16",
          5.17,
          "שקל חדש",
          4.6,
          3.43,
          230300,
          108.61,
          250.12883,
          0.04,
          4.46,
          0.06
        ],
        [
          "שמוס אגח א רמ- Chamoss International Limited",
          1147578,
          "אחר",
          1742,
          "נדל\"ן ובינוי",
          "Aa3.IL",
          "מידרוג",
          "11/06/18",
          6.64,
          "שקל חדש",
          5.1,
          4.48,
          2900000,
          100.26,
          2907.54,
          0.2,
          51.83,
          0.76
        ]
      ]
    },
    "לא סחיר - מניות": {
      "columns": [
        "שם המנפיק/שם נייר ערך",
        "מספר ני\"ע",
        "ספק המידע",
        "מספר מנפיק",
        "ענף מסחר",
        "סוג מטבע",
        "ערך נקוב",
        "שער",
        "שווי הוגן",
        "שעור מערך נקוב מונפק",
        "שעור מנכסי אפיק ההשקעה",
        "שעור מסך נכסי השקעה"
      ],
      "data": [
        [
          "נארה מדיקל סנטר בע\"מ- נארה מדיקל סנטר בע\"מ",
          29992737,
          "אחר",
          515138584,
          "Health Care Equipment & Services",
          "שקל חדש",
          153.05,
          83677.308,
          128.068119894,
          0.08,
          11.27,
          0.03
        ],
        [
          "Project Home Hema Retail- HDR AS 1 s.a.r.l",
          29992735,
          "אחר",
          13034,
          "Real Estate",
          "אירו",
          87.09,
          261469.2,
          962.271819354024,
          0.11,
          84.65,
          0.25
        ],
        [
          "Energy Vision Limited- Energy Vision",
          29992742,
          "אחר",
          13038,
          "Utilities",
          "דולר אמריקאי",
          140.69,
          9044.344,
          46.4316551560664,
          0.01,
          4.08,
          0.01
        ]
      ]
    },
    "לא סחיר - קרנות השקעה": {
      "columns": [
        "שם המנפיק/שם נייר ערך",
        "מספר ני\"ע",
        "סוג מטבע",
        "תאריך רכישה",
        "ערך נקוב",
        "שער",
        "שווי הוגן",
        "שעור מערך נקוב מונפק",
        "שעור מנכסי אפיק ההשקעה",
        "שעור מסך נכסי השקעה"
      ],
      "data": [
        [
          "AP Partners- Ap Partners",
          29992997,
          "שקל חדש",
          "02/05/18",
          19304.0,
          100.0,
          19.304,
          0.19,
          0.44,
          0.01
        ],
        [
          "קרן השקעה Copia- Copia",
          29993135,
          "דולר אמריקאי",
          "22/05/18",
          2846.25,
          100.0,
          10.38596625,
          0.08,
          0.24,
          0.0
        ],
        [
          "Stage one 3- stage one1",
          29992953,
          "דולר אמריקאי",
          "16/01/18",
          490.91,
          99.509,
          1.7825351568031,
          0.02,
          0.04,
          0.0
        ],
        [
          "פונטיפקס V- פונטיפקס 2 שירותי ניהול הקרן (2007) בע\"מ",
          29992982,
          "דולר אמריקאי",
          "22/03/18",
          7333.33,
          100.0,
          26.75932117,
          0.0,
          0.61,
          0.01
        ],
        [
          "יסודות א נדלן ופיתוח אנקס 1 שותפות מוגבלת- יסודות א נדלן שותפות מוגבלת",
          29992728,
          "שקל חדש",
          "09/11/16",
          224066.69,
          113.452,
          254.2081411388,
          0.18,
          5.83,
          0.07
        ],
        [
          "קרן יסודות נדלן  ב- יסודות א נדלן שותפות מוגבלת",
          29992954,
          "שקל חדש",
          "25/01/18",
          327871.2,
          99.873,
          327.454803576,
          0.11,
          7.51,
          0.09
        ],
        [
          "Noy 2 Infrastructure and Energy Investments Fund- קרן נוי 1 להשקעה בתשתיות אנרגיה ש.מ",
          29992822,
          "שקל חדש",
          "28/12/17",
          46047.02,
          95.617,
          44.0287791134,
          0.01,
          1.01,
          0.01
        ],
        [
          "Noy negev energy limited partnership- קרן נוי 1 להשקעה בתשתיות אנרגיה ש.מ",
          29992710,
          "שקל חדש",
          "04/08/16",
          45048.0,
          115.922,
          52.22054256,
          0.02,
          1.2,
          0.01
        ],
        [
          "נוי כוכב הירדן- קרן נוי 1 להשקעה בתשתיות אנרגיה ש.מ",
          29992808,
          "שקל חדש",
          "30/11/17",
          133184.0,
          103.684,
          138.09049856,
          0.1,
          3.17,
          0.04
        ],
        [
          "קרן נוי 1 להשקעה בתשתיות אנרגיה פש\"ה- קרן נוי 1 להשקעה בתשתיות אנרגיה ש.מ",
          29992821,
          "שקל חדש",
          "28/12/17",
          89420.0,
          136.764,
          122.2943688,
          0.02,
          2.8,
          0.03
        ],
        [
          "Aurum Isis fund institutional Iti dollar- Aurum Isis Fund",
          299927080,
          "דולר אמריקאי",
          "18/09/16",
          33.0,
          111250.74,
          133.9648035858,
          0.0,
          3.07,
          0.03
        ],
        [
          "BK opportunity 4- BK Opportunities fund",
          29992769,
          "דולר אמריקאי",
          "24/04/17",
          257803.92,
          110.73205899999968,
          1041.6858275265,
          0.44,
          23.88,
          0.27
        ],
        [
          "Blackrock european hedge fund limitited- class I- Blackrock european hedge fund",
          299927230,
          "אירו",
          "10/11/16",
          78.93,
          28613.655999999988,
          95.4386732333246,
          0.0,
          2.19,
          0.02
        ],
        [
          "קרן גידורPI- PI",
          299927040,
          "דולר אמריקאי",
          "11/09/16",
          30.0,
          104695.46,
          114.610120062,
          0.0,
          2.63,
          0.03
        ],
        [
          "*אורקה לונג שורט- אורקה לונג שורט",
          299928290,
          "דולר אמריקאי",
          "20/02/18",
          70.67,
          98327.94,
          253.563008117502,
          0.0,
          5.81,
          0.07
        ],
        [
          "1 MBP REAL ESTATE FUND- MBP REAL ESTATE FUND 1",
          29992977,
          "דולר אמריקאי",
          "06/03/18",
          31054.24,
          99.45800000000018,
          112.702744044061,
          0.12,
          2.58,
          0.03
        ],
        [
          "Investcorp Special Opportunities Italian- Investcorp Investment Advisers Limited",
          29992801,
          "אירו",
          "30/10/17",
          106727.53,
          101.47800000000007,
          457.67511219493,
          0.14,
          10.49,
          0.12
        ],
        [
          "Anacap credit opportunities III- AnaCap Credit Opportunities GP III, L.P",
          29992706,
          "אירו",
          "11/07/16",
          7756.31,
          162.78899999999993,
          53.3567234635162,
          0.0,
          1.22,
          0.01
        ],
        [
          "Crescent mezzanine parners VII- Crescent mezzanine partners",
          29992743,
          "דולר אמריקאי",
          "08/02/17",
          52361.39,
          91.65099999999995,
          175.114552315936,
          0.0,
          4.01,
          0.05
        ],
        [
          "Forma Fund I l.p- Forma Fund",
          29992780,
          "אירו",
          "14/06/17",
          150403.57,
          95.36500000000001,
          606.116486032987,
          0.18,
          13.89,
          0.16
        ],
        [
          "Gatewood Capital Opportunity Fund (Cayman) LP- Gatewood Capital Opportunity Fund",
          29992724,
          "דולר אמריקאי",
          "13/10/16",
          3872.33,
          118.894,
          16.7998793421998,
          0.01,
          0.39,
          0.0
        ],
        [
          "ICG Strategic Secondaries Fund II- ICG Fund",
          29992777,
          "דולר אמריקאי",
          "07/06/17",
          32103.0,
          149.103,
          174.66499019241,
          0.01,
          4.0,
          0.05
        ],
        [
          "Signal Real Estate Opporyunities Fund- Signal Real Estate Opportunities Fund",
          29992791,
          "אירו",
          "09/08/17",
          24686.56,
          125.35600000000011,
          130.771962416283,
          0.01,
          3.0,
          0.03
        ]
      ]
    },
    "לא סחיר - כתבי אופציה": {
      "columns": [
        "שם המנפיק/שם נייר ערך",
        "מספר ני\"ע",
        "ענף מסחר",
        "סוג מטבע",
        "תאריך רכישה",
        "ערך נקוב",
        "שער",
        "שווי הוגן",
        "שעור מערך נקוב מונפק",
        "שעור מנכסי אפיק ההשקעה",
        "שעור מסך נכסי השקעה"
      ],
      "data": [
        [
          "אליהו כתב אופ 1- אליהו חברה לביטוח",
          299927950,
          "השקעה ואחזקות",
          "שקל חדש",
          "28/09/17",
          65436,
          4.22,
          2.7613992,
          0,
          12.1,
          0
        ],
        [
          "אליהו כתב אופ 2- אליהו חברה לביטוח",
          299927960,
          "השקעה ואחזקות",
          "שקל חדש",
          "28/09/17",
          65436,
          11.45,
          7.492422,
          0,
          32.83,
          0
        ],
        [
          "אליהו כתב אופ 3- אליהו חברה לביטוח",
          299927970,
          "השקעה ואחזקות",
          "שקל חדש",
          "28/09/17",
          65436,
          19.21,
          12.5702556,
          0,
          55.07,
          0
        ]
      ]
    },
    "לא סחיר - אופציות": {
      "columns": [
        "שם המנפיק/שם נייר ערך",
        "מספר ני\"ע",
        "ענף מסחר",
        "סוג מטבע",
        "תאריך רכישה",
        "ערך נקוב",
        "שער",
        "שווי הוגן",
        "שעור מערך נקוב מונפק",
        "שעור מנכסי אפיק ההשקעה",
        "שעור מסך נכסי השקעה"
      ],
      "data": [
        [
          "אופציה לס דולר שקל C345 24/07/18- חוזים סחירים ואופציות בישראל",
          29992959,
          "אחר",
          "דולר אמריקאי",
          "06/02/18",
          -294000,
          5.2864,
          -56.712816384,
          0,
          168.67,
          -0.01
        ],
        [
          "אופציה לס דולר שקל C345 28/08/18- חוזים סחירים ואופציות בישראל",
          29992967,
          "אחר",
          "דולר אמריקאי",
          "07/02/18",
          -294000,
          5.0778,
          -54.474943068,
          0,
          162.01,
          -0.01
        ],
        [
          "אופציה לס דולר שקל C350 27/11/18- חוזים סחירים ואופציות בישראל",
          29992983,
          "אחר",
          "דולר אמריקאי",
          "28/03/18",
          -285000,
          3.6044,
          -37.48449846,
          0,
          111.48,
          -0.01
        ],
        [
          "אופציה לס דולר שקל C350 31/10/18- חוזים סחירים ואופציות בישראל",
          29992970,
          "אחר",
          "דולר אמריקאי",
          "08/02/18",
          -294000,
          3.65,
          -39.157419,
          0,
          116.46,
          -0.01
        ],
        [
          "אופציה לס דולר שקל C360 24/07/18- חוזים סחירים ואופציות בישראל",
          29992960,
          "אחר",
          "דולר אמריקאי",
          "06/02/18",
          294000,
          1.4284,
          15.323960904,
          0,
          -45.57,
          0.0
        ],
        [
          "אופציה לס דולר שקל C360 28/08/18- חוזים סחירים ואופציות בישראל",
          29992968,
          "אחר",
          "דולר אמריקאי",
          "07/02/18",
          294000,
          1.5699,
          16.841981394,
          0,
          -50.09,
          0.0
        ],
        [
          "אופציה לס דולר שקל C370 27/11/18- חוזים סחירים ואופציות בישראל",
          29992984,
          "אחר",
          "דולר אמריקאי",
          "28/03/18",
          1728000,
          0.8464,
          53.369515008,
          0,
          -158.72,
          0.01
        ],
        [
          "אופציה לס דולר שקל C375 30/10/18- חוזים סחירים ואופציות בישראל",
          29992971,
          "אחר",
          "דולר אמריקאי",
          "08/02/18",
          2940000,
          0.4995,
          53.5866597,
          0,
          -159.37,
          0.01
        ],
        [
          "אופציה לס דולר שקל P335 24/07/18- חוזים סחירים ואופציות בישראל",
          29992961,
          "אחר",
          "דולר אמריקאי",
          "06/02/18",
          1176000,
          0.0001,
          0.004291224,
          0,
          -0.01,
          0.0
        ],
        [
          "אופציה לס דולר שקל P335 27/11/18- חוזים סחירים ואופציות בישראל",
          29992985,
          "אחר",
          "דולר אמריקאי",
          "28/03/18",
          1140000,
          0.1027,
          4.27217622,
          0,
          -12.71,
          0.0
        ],
        [
          "אופציה לס דולר שקל P335 28/08/18- חוזים סחירים ואופציות בישראל",
          29992969,
          "אחר",
          "דולר אמריקאי",
          "07/02/18",
          1176000,
          0.0017,
          0.072950808,
          0,
          -0.22,
          0.0
        ],
        [
          "אופציה לס דולר שקל P340 30/10/18- חוזים סחירים ואופציות בישראל",
          29992972,
          "אחר",
          "דולר אמריקאי",
          "08/02/18",
          1176000,
          0.1147,
          4.922033928,
          0,
          -14.64,
          0.0
        ],
        [
          "Energy ev1  option- Energy Vision",
          29992820,
          "Utilities",
          "דולר אמריקאי",
          "20/12/17",
          95,
          1676.6,
          5.81201773,
          0,
          -17.29,
          0.0
        ]
      ]
    },
    "לא סחיר - חוזים עתידיים": {
      "columns": [
        "שם המנפיק/שם נייר ערך",
        "מספר ני\"ע",
        "ענף מסחר",
        "סוג מטבע",
        "תאריך רכישה",
        "ערך נקוב",
        "שער",
        "שווי הוגן",
        "שעור מנכסי אפיק ההשקעה",
        "שעור מסך נכסי השקעה"
      ],
      "data": [
        [
          "FWD CCY\\ILS 20180111 USD\\ILS 3.3586 20190111- בנק לאומי לישראל בע\"מ",
          90005881,
          "ל.ר.",
          "דולר אמריקאי",
          "11/01/18",
          -589900.0,
          24.037770541082217,
          -141.798808421844,
          12.49,
          -0.04
        ],
        [
          "FWD CCY\\ILS 20180201 USD\\ILS 3.3666000 20190111- בנק לאומי לישראל בע\"מ",
          90006026,
          "ל.ר.",
          "דולר אמריקאי",
          "01/02/18",
          -247800.0,
          23.237244929797214,
          -57.5818929360375,
          5.07,
          -0.01
        ],
        [
          "FWD CCY\\ILS 20180212 EUR\\ILS 4.3489000 20190213- בנק לאומי לישראל בע\"מ",
          90006095,
          "ל.ר.",
          "אירו",
          "12/02/18",
          -40500.0,
          -11.354792243767308,
          4.59869085872576,
          -0.41,
          0.0
        ],
        [
          "FWD CCY\\ILS 20180213 EUR\\ILS 4.3704000 20190213- בנק לאומי לישראל בע\"מ",
          90006114,
          "ל.ר.",
          "אירו",
          "13/02/18",
          -835500.0,
          -13.506163604549371,
          112.84399691601,
          -9.94,
          0.03
        ],
        [
          "FWD CCY\\ILS 20180409 EUR\\ILS 4.3558000 20190410- בנק לאומי לישראל בע\"מ",
          90006408,
          "ל.ר.",
          "אירו",
          "09/04/18",
          -674600.0,
          -11.717649402390395,
          79.0472628685256,
          -6.97,
          0.02
        ],
        [
          "FWD CCY\\ILS 20180423 USD\\ILS 3.4823000 20190111- בנק לאומי לישראל בע\"מ",
          90006482,
          "ל.ר.",
          "דולר אמריקאי",
          "23/04/18",
          -548100.0,
          11.659667300380205,
          -63.9066364733839,
          5.63,
          -0.02
        ],
        [
          "FWD CCY\\ILS 20180430 EUR\\ILS 4.3690000 20190213- בנק לאומי לישראל בע\"מ",
          90006502,
          "ל.ר.",
          "אירו",
          "30/04/18",
          -417300.0,
          -13.366072300928206,
          55.7766197117734,
          -4.91,
          0.01
        ],
        [
          "FWD CCY\\ILS 20180605 GBP\\ILS 4.7317300 20190605- בנק לאומי לישראל בע\"מ",
          90006702,
          "ל.ר.",
          "לירה שטרלינג",
          "05/06/18",
          -606700.0,
          0.5425169918877435,
          -3.29145058978294,
          0.29,
          0.0
        ],
        [
          "FWD CCY\\ILS 20180612 EUR\\ILS 4.2400000 20190614- בנק לאומי לישראל בע\"מ",
          90006744,
          "ל.ר.",
          "אירו",
          "12/06/18",
          -144900.0,
          0.21051643192488337,
          -0.305038309859156,
          0.03,
          0.0
        ],
        [
          "FWD CCY\\ILS 20180612 EUR\\ILS 4.2405000 20190614- בנק לאומי לישראל בע\"מ",
          90006743,
          "ל.ר.",
          "אירו",
          "12/06/18",
          -111100.0,
          0.16050412217867327,
          -0.178320079740506,
          0.02,
          0.0
        ],
        [
          "FWD CCY\\ILS 20180618 EUR\\ILS 4.2218000 20190410- בנק לאומי לישראל בע\"מ",
          90006762,
          "ל.ר.",
          "אירו",
          "18/06/18",
          -380000.38,
          1.6894419434877301,
          -6.41988580513276,
          0.57,
          0.0
        ],
        [
          "FWD CCY\\ILS 20180627 EUR\\ILS 4.2620000 20190213- בנק לאומי לישראל בע\"מ",
          90006817,
          "ל.ר.",
          "אירו",
          "27/06/18",
          -82000.0,
          -2.6592763157894757,
          2.18060657894737,
          -0.19,
          0.0
        ],
        [
          "FWD CCY\\ILS 20180628 EUR\\ILS 4.2285000 20180629 SP- בנק לאומי לישראל בע\"מ",
          90006832,
          "ל.ר.",
          "אירו",
          "28/06/18",
          -162900.0,
          -0.2661674008810571,
          0.433586696035242,
          -0.04,
          0.0
        ],
        [
          "FWD CCY\\ILS 20180628 EUR\\ILS 4.2292000 20180629 SP- בנק לאומי לישראל בע\"מ",
          90006827,
          "ל.ר.",
          "אירו",
          "28/06/18",
          -0.16,
          -0.3338898163606013,
          5.34223706176962e-07,
          0.0,
          0.0
        ],
        [
          "FWD CCY\\ILS 20180628 EUR\\ILS 4.2455000 20190614- בנק לאומי לישראל בע\"מ",
          90006833,
          "ל.ר.",
          "אירו",
          "28/06/18",
          162900.0,
          -0.3397092511013223,
          -0.553386370044054,
          0.05,
          0.0
        ],
        [
          "FWD CCY\\ILS 20180628 EUR\\ILS 4.2470000 20190614- בנק לאומי לישראל בע\"מ",
          90006834,
          "ל.ר.",
          "אירו",
          "28/06/18",
          93100.0,
          -0.48975384615384643,
          -0.455960830769231,
          0.04,
          0.0
        ],
        [
          "004 20250831 ILS ILS TELBOR FLOAT FIXED 0 1.2915- בנק לאומי לישראל בע\"מ",
          90005068,
          "ל.ר.",
          "שקל חדש",
          "19/09/17",
          717000.0,
          1.1229220779220794,
          8.05135129870131,
          -0.71,
          0.0
        ],
        [
          "004 20250831 ILS ILS TELBOR FLOAT FIXED 0 1.435- בנק לאומי לישראל בע\"מ",
          90004786,
          "ל.ר.",
          "שקל חדש",
          "09/08/17",
          270000.0,
          -0.06610526315789482,
          -0.178484210526316,
          0.02,
          0.0
        ],
        [
          "004 20250831 ILS ILS TELBOR FLOAT FIXED 0 1.53- בנק לאומי לישראל בע\"מ",
          90002818,
          "ל.ר.",
          "שקל חדש",
          "16/11/16",
          4011000.0,
          -0.7947362637362628,
          -31.8768715384615,
          2.81,
          -0.01
        ],
        [
          "004 20250831 ILS ILS TELBOR FLOAT FIXED 0 1.58- בנק לאומי לישראל בע\"מ",
          90004429,
          "ל.ר.",
          "שקל חדש",
          "21/06/17",
          335000.0,
          -1.1782221105527613,
          -3.94704407035175,
          0.35,
          0.0
        ],
        [
          "004 20250831 ILS ILS TELBOR FLOAT FIXED 0 1.619- בנק לאומי לישראל בע\"מ",
          90004751,
          "ל.ר.",
          "שקל חדש",
          "07/08/17",
          320000.0,
          -1.4773384135781094,
          -4.72748292344995,
          0.42,
          0.0
        ],
        [
          "004 20250831 ILS ILS TELBOR FLOAT FIXED 0 1.715- בנק לאומי לישראל בע\"מ",
          90002823,
          "ל.ר.",
          "שקל חדש",
          "16/11/16",
          2304000.0,
          -2.2136237373737413,
          -51.001890909091,
          4.49,
          -0.01
        ],
        [
          "004 20250831 ILS ILS TELBOR FLOAT FIXED 0 1.755- בנק לאומי לישראל בע\"מ",
          90004016,
          "ל.ר.",
          "שקל חדש",
          "24/04/17",
          152000.0,
          -2.5204110429447897,
          -3.83102478527608,
          0.34,
          0.0
        ],
        [
          "004 20250831 ILS ILS TELBOR FLOAT FIXED 0 1.87- בנק לאומי לישראל בע\"מ",
          90003581,
          "ל.ר.",
          "שקל חדש",
          "16/02/17",
          6222000.0,
          -3.4024375,
          -211.69966125,
          18.65,
          -0.05
        ],
        [
          "004 20250831 ILS ILS TELBOR FLOAT FIXED 0 2.035- בנק לאומי לישראל בע\"מ",
          90003139,
          "ל.ר.",
          "שקל חדש",
          "15/12/16",
          3033000.0,
          -4.667929936305737,
          -141.578314968153,
          12.48,
          -0.04
        ],
        [
          "004 20250831 ILS ILS TELBOR FLOAT FIXED 0 1.457- חוזים סחירים ואופציות בישראל",
          90004616,
          "ל.ר.",
          "שקל חדש",
          "18/07/17",
          422000.0,
          -0.23483870967741896,
          -0.991019354838708,
          0.09,
          0.0
        ],
        [
          "004 20250831 ILS ILS TELBOR FLOAT FIXED 0 1.695- חוזים סחירים ואופציות בישראל",
          90003972,
          "ל.ר.",
          "שקל חדש",
          "13/04/17",
          500000.0,
          -2.06023026315788,
          -10.3011513157894,
          0.91,
          0.0
        ],
        [
          "004 20250831 ILS ILS TELBOR FLOAT FIXED 0 1.725- חוזים סחירים ואופציות בישראל",
          90004112,
          "ל.ר.",
          "שקל חדש",
          "08/05/17",
          360000.0,
          -2.2903231292517,
          -8.24516326530612,
          0.73,
          0.0
        ],
        [
          "004 20250831 ILS ILS TELBOR FLOAT FIXED 0 1.755- חוזים סחירים ואופציות בישראל",
          90003879,
          "ל.ר.",
          "שקל חדש",
          "23/03/17",
          942000.0,
          -2.5204071428571444,
          -23.7422352857143,
          2.09,
          -0.01
        ],
        [
          "004 20250831 ILS ILS TELBOR FLOAT FIXED 0 1.775- חוזים סחירים ואופציות בישראל",
          90003922,
          "ל.ר.",
          "שקל חדש",
          "30/03/17",
          475000.0,
          -2.6738133333333263,
          -12.7006133333333,
          1.12,
          0.0
        ],
        [
          "004 20250831 ILS ILS TELBOR FLOAT FIXED 0 1.875- חוזים סחירים ואופציות בישראל",
          90003784,
          "ל.ר.",
          "שקל חדש",
          "15/03/17",
          1599000.0,
          -3.4407695961995186,
          -55.0179058432303,
          4.85,
          -0.01
        ],
        [
          "004 20250831 ILS ILS TELBOR FLOAT FIXED 0 1.98- חוזים עתידיים בחול",
          90003110,
          "ל.ר.",
          "שקל חדש",
          "12/12/16",
          13270000.0,
          -4.246090909090912,
          -563.456263636364,
          49.65,
          -0.15
        ]
      ]
    },
    "לא סחיר - מוצרים מובנים": {
      "columns": [
        "שם המנפיק/שם נייר ערך",
        "מספר ני\"ע",
        "נכס הבסיס",
        "דירוג",
        "שם מדרג",
        "תאריך רכישה",
        "מח\"מ",
        "סוג מטבע",
        "שיעור ריבית",
        "תשואה לפידיון",
        "ערך נקוב",
        "שער",
        "שווי הוגן",
        "שעור מערך נקוב מונפק",
        "שעור מנכסי אפיק ההשקעה",
        "שעור מסך נכסי השקעה"
      ],
      "data": [
        [
          "AESOP 2016-2X A- Avis Budget Rental Car Funding",
          "usu05376cg81",
          "אשראי",
          "AAA",
          "S&P",
          "26/05/16",
          4.15,
          "דולר אמריקאי",
          2.72,
          3.05,
          22000,
          97.7,
          78.431606,
          0.01,
          100,
          0.02
        ]
      ]
    },
    "הלוואות": {
      "columns": [
        "שם המנפיק/שם נייר ערך",
        "קונסורציום כן/לא",
        "מספר ני\"ע",
        "מספר מנפיק",
        "דירוג",
        "תאריך רכישה",
        "שם מדרג",
        "מח\"מ",
        "סוג מטבע",
        "שיעור ריבית ממוצע",
        "תשואה לפידיון",
        "ערך נקוב",
        "שער",
        "שווי הוגן",
        "שעור מנכסי אפיק ההשקעה",
        "שעור מסך נכסי השקעה",
        "מעלות",
        "שקל חדש"
      ],
      "data": [
        [
          "הלוואה 52 06/2018",
          "כן",
          29993150,
          500286000,
          "AAA",
          "28/06/18",
          "פנימי",
          6.78,
          "שקל חדש",
          1.57,
          1.6,
          109387.0,
          100.0,
          109.387,
          1.66,
          0.03,
          "",
          ""
        ],
        [
          "הלוואה 38 01/2018",
          "כן",
          29992951,
          5957517,
          "AA+",
          "16/01/18",
          "פנימי",
          5.18,
          "שקל חדש",
          2.82,
          3.23,
          99701.4,
          99.23,
          98.93369922,
          1.51,
          0.03,
          "",
          ""
        ],
        [
          "הלוואה 39 01/2018",
          "כן",
          29992952,
          5957517,
          "AA+",
          "16/01/18",
          "פנימי",
          5.13,
          "שקל חדש",
          2.82,
          3.61,
          99701.4,
          96.49,
          96.20188086,
          1.46,
          0.02,
          "",
          ""
        ],
        [
          "הלוואה 41 02/2018",
          "כן",
          29992974,
          13067,
          "AA",
          "19/02/18",
          "פנימי",
          3.12,
          "שקל חדש",
          2.1,
          3.28,
          47583.0,
          99.62,
          47.4021846,
          0.72,
          0.01,
          "",
          ""
        ],
        [
          "הלוואה 42 02/2018",
          "כן",
          29992973,
          13067,
          "AA",
          "19/02/18",
          "פנימי",
          3.74,
          "שקל חדש",
          3.44,
          2.0,
          203892.0,
          107.16,
          218.4906672,
          3.33,
          0.06,
          "",
          ""
        ],
        [
          "הלוואה 46 03/2018",
          "כן",
          29992981,
          13072,
          "AA",
          "14/03/18",
          "פנימי",
          5.12,
          "שקל חדש",
          3.34,
          3.62,
          37956.43,
          99.1,
          37.61482213,
          0.57,
          0.01,
          "",
          ""
        ],
        [
          "הלוואה 49 06/2018",
          "כן",
          29993142,
          511914178,
          "AA",
          "13/06/18",
          "פנימי",
          5.84,
          "שקל חדש",
          2.59,
          2.68,
          30765.0,
          100.96,
          31.060344,
          0.47,
          0.01,
          "",
          ""
        ],
        [
          "הלוואה 34.1 03/2017",
          "לא",
          29992756,
          520038506,
          "AA-.IL",
          "23/03/17",
          "S&P מעלות",
          1.57,
          "שקל חדש",
          0.25,
          0.36,
          2807000.0,
          100.06095890274314,
          2808.7111164,
          42.75,
          0.73,
          "",
          ""
        ],
        [
          "הלוואה 34.1 03/2017",
          "לא",
          29992757,
          520038506,
          "AA-.IL",
          "23/03/17",
          "S&P מעלות",
          2.58,
          "שקל חדש",
          0.25,
          0.0,
          -2807000.0,
          100.0,
          -2807.0,
          -42.72,
          -0.73,
          "",
          ""
        ],
        [
          "הלוואה 36 08/2017",
          "לא",
          29992786,
          13055,
          0,
          "03/08/17",
          "לא מדורג",
          3.71,
          "שקל חדש",
          5.0,
          4.13,
          390000.0,
          105.85,
          412.815,
          6.28,
          0.11,
          "",
          ""
        ],
        [
          "הלוואה 47.1 05/2018",
          "כן",
          29993136,
          221942,
          0,
          "28/05/18",
          "לא מדורג",
          3.37,
          "דולר אמריקאי",
          1.13,
          1.22,
          771000.0,
          100.0678082230869,
          2815.2867023086,
          42.85,
          0.73,
          "",
          ""
        ],
        [
          "הלוואה 47.2 05/2018",
          "כן",
          29993137,
          221942,
          0,
          "28/05/18",
          "לא מדורג",
          "",
          "דולר אמריקאי",
          0.0,
          0.0,
          -771000.0,
          100.0,
          -2813.379,
          -42.82,
          -0.73,
          "",
          ""
        ],
        [
          "הלוואה 50 06/2018",
          "כן",
          29993143,
          "",
          "AA",
          "18/06/18",
          "פנימי",
          4.4,
          "אירו",
          2.3,
          2.56,
          188410.34,
          99.92260515642228,
          795.568209089597,
          12.11,
          0.21,
          "",
          ""
        ],
        [
          "הלוואה 51 06/2018",
          "כן",
          29993144,
          "",
          "AA",
          "18/06/18",
          "פנימי",
          4.4,
          "אירו",
          2.35,
          2.61,
          191589.66,
          99.92423917524262,
          809.006210752834,
          12.31,
          0.21,
          "",
          ""
        ],
        [
          "הלוואה 35 04/2017",
          "כן",
          29992774,
          194680,
          "BBB",
          "20/09/17",
          "S&P",
          0.76,
          "לירה שטרלינג",
          5.67,
          5.87,
          127056.39,
          102.38518850383309,
          621.165064046602,
          9.45,
          0.16,
          "",
          ""
        ],
        [
          "הלוואה 35.1 04/2017",
          "כן",
          29992772,
          194680,
          "BBB",
          "30/04/17",
          "S&P",
          0.75,
          "לירה שטרלינג",
          1.0,
          1.04,
          76943.6,
          100.0,
          367.40569,
          5.59,
          0.1,
          "",
          ""
        ],
        [
          "הלוואה 35.2 04/2017",
          "כן",
          29992773,
          194680,
          "BBB",
          "30/04/17",
          "S&P",
          1.75,
          "לירה שטרלינג",
          0.0,
          0.0,
          -76943.6,
          100.0,
          -367.40569,
          -5.59,
          -0.1,
          "",
          ""
        ],
        [
          "הלוואה 43 02/2018",
          "כן",
          29992975,
          "",
          "Baa2",
          "22/02/18",
          "Moodys",
          2.05,
          "דולר אמריקאי",
          6.59,
          7.85,
          169000.0,
          99.55388819094004,
          613.929913234771,
          9.34,
          0.16,
          "",
          ""
        ],
        [
          "הלוואה 33 02/2017",
          "כן",
          29992749,
          67011330,
          "B",
          "23/02/17",
          "S&P",
          4.64,
          "אירו",
          5.25,
          5.41,
          175000.0,
          100.63662607197203,
          744.222945296144,
          11.33,
          0.19,
          "",
          ""
        ],
        [
          "הלוואה 37 08/2017",
          "כן",
          29992787,
          814070775,
          0,
          "03/08/17",
          "לא מדורג",
          1.88,
          "דולר אמריקאי",
          6.09,
          6.89,
          186766.43,
          100.26978611443703,
          683.349324315285,
          10.4,
          0.18,
          "",
          ""
        ],
        [
          "הלוואה 40 01/2018",
          "כן",
          29992955,
          "",
          0,
          "29/01/18",
          "לא מדורג",
          1.23,
          "דולר אמריקאי",
          4.54,
          5.61,
          113900.0,
          99.81476772030054,
          414.851235561558,
          6.31,
          0.11,
          "",
          ""
        ],
        [
          "הלוואה 44 03/2018",
          "כן",
          29992978,
          "",
          0,
          "08/03/18",
          "לא מדורג",
          1.22,
          "דולר אוסטרלי",
          10.5,
          10.83,
          169000.0,
          99.64004589082273,
          451.188660842181,
          6.87,
          0.12,
          "",
          ""
        ],
        [
          "הלוואה 45 03/2018",
          "כן",
          29992979,
          "",
          0,
          "09/03/18",
          "לא מדורג",
          0.6,
          "דולר אמריקאי",
          6.34,
          7.15,
          102858.43,
          101.7808685704299,
          382.014552396011,
          5.81,
          0.1,
          "",
          ""
        ]
      ]
    },
    "פקדונות מעל 3 חודשים": {
      "columns": [
        "שם המנפיק/שם נייר ערך",
        "מספר ני\"ע",
        "מספר מנפיק",
        "דירוג",
        "שם מדרג",
        "מח\"מ",
        "סוג מטבע",
        "תנאי ושיעור ריבית",
        "תשואה לפידיון",
        "ערך נקוב",
        "שער",
        "שווי הוגן",
        "שעור מנכסי אפיק ההשקעה",
        "שעור מסך נכסי השקעה"
      ],
      "data": [
        [
          "ביטחונות CSA במטבע 20001 (OTC)- בנק לאומי לישראל בע\"מ",
          77720001,
          10,
          "AAA.IL",
          "S&P מעלות",
          0.01,
          "דולר אמריקאי",
          0,
          0.01,
          300000.0,
          100,
          1094.7,
          30.56,
          0.28
        ],
        [
          "ביטחונות חוזים עתידיים במטבע 20001",
          88820001,
          10,
          "AAA.IL",
          "S&P מעלות",
          0.01,
          "דולר אמריקאי",
          0,
          0.01,
          681659.18,
          100,
          2487.37434782,
          69.44,
          0.65
        ]
      ]
    },
    "השקעות אחרות ": {
      "columns": [
        "שם המנפיק/שם נייר ערך",
        "מספר ני\"ע",
        "דירוג",
        "שם המדרג",
        "שעור הריבית",
        "סוג מטבע",
        "תשואה לפדיון",
        "שווי הוגן",
        "שעור מנכסי אפיק ההשקעה",
        "שעור מסך נכסי השקעה"
      ],
      "data": [
        [
          "זכאים",
          28080000,
          0,
          "לא מדורג",
          0,
          "שקל חדש",
          0,
          -1.37001,
          205.44,
          0
        ],
        [
          "זכאים מס עמיתים",
          28200000,
          0,
          "לא מדורג",
          0,
          "שקל חדש",
          0,
          -0.2151,
          32.26,
          0
        ],
        [
          "חייבים",
          27960000,
          0,
          "לא מדורג",
          0,
          "שקל חדש",
          0,
          0.91118,
          -136.64,
          0
        ],
        [
          "Samsung electronics(דיבידנד לקבל)",
          704519500,
          0,
          "לא מדורג",
          0,
          "דולר אמריקאי",
          0,
          0.00707906,
          -1.06,
          0
        ]
      ]
    },
    "יתרת התחייבות להשקעה": {
      "columns": [
        "שם המנפיק/שם נייר ערך",
        "סכום ההתחייבות",
        "תאריך סיום ההתחייבות"
      ],
      "data": [
        [
          "אביב 2",
          0.0,
          43040
        ],
        [
          "אוריגו",
          0.0,
          43245
        ],
        [
          "גלילות 1",
          0.0,
          43313
        ],
        [
          "גלילות 2",
          0.0,
          44713
        ],
        [
          "גלילות - שותפות 1",
          0.0,
          "עד למועד פירוק שותפות"
        ],
        [
          "יסודות",
          0.0,
          44166
        ],
        [
          "Klirmark 1",
          0.0,
          43160
        ],
        [
          "Klirmark 2",
          0.0,
          44835
        ],
        [
          "לול",
          0.0,
          43770
        ],
        [
          "מאגמה",
          0.0,
          45536
        ],
        [
          "מוסטנג",
          0.0,
          43344
        ],
        [
          "נווה אילן",
          0.0,
          "עד למועד פירוק שותפות"
        ],
        [
          "נוי 1 תשתיות ואנרגיה",
          0.0,
          44409
        ],
        [
          "נוי 2 תשתיות ואנרגיה",
          0.0,
          "עד למועד פירוק שותפות"
        ],
        [
          "סקי",
          0.0,
          42948
        ],
        [
          "פונטיפקס II",
          0.0,
          42887
        ],
        [
          "פונטיפקס III",
          0.0,
          44470
        ],
        [
          "פונטיפקס 4",
          0.0,
          44105
        ],
        [
          "פימי 2",
          0.0,
          42644
        ],
        [
          "פימי 5",
          0.0,
          44774
        ],
        [
          "ריאלטי 1",
          0.0,
          43282
        ],
        [
          "ריאלטי 2",
          0.0,
          44593
        ],
        [
          "ריאלטי 3",
          0.0,
          44713
        ],
        [
          "STATE OF MIND VENTURES",
          0.0,
          44440
        ],
        [
          "תשתיות לישראל 2",
          0.0,
          44409
        ],
        [
          "ISF",
          0.0,
          45627
        ],
        [
          "KCPS",
          0.0,
          43221
        ],
        [
          "KEDMA 2",
          0.0,
          45748
        ],
        [
          "Vintage",
          0.0,
          43344
        ],
        [
          "קוגיטו קפיטל (קרן להלוואות לעסקים קטנים)",
          0.0,
          43891
        ],
        [
          "בנק דקסיה",
          1386.6887707399999,
          47515
        ],
        [
          "הלוואה 34 03/2017 אלוני חץ",
          2807.0,
          43855
        ],
        [
          "נוי נגב אנרגיה",
          53.249,
          "עד למועד פירוק השותפות"
        ],
        [
          "פנינסולה",
          0.0,
          44256
        ],
        [
          "GATEWOOD",
          56.672613404399996,
          46174
        ],
        [
          "יסודות אנקס",
          293.93330930985917,
          44166
        ],
        [
          "FORMA",
          21.456297320566332,
          46631
        ],
        [
          "קרן קוגיטו משלימה",
          28.233796269066566,
          47119
        ],
        [
          "נוי כוכב הירדן",
          305.217873411382,
          "עד למועד פירוק השותפות"
        ],
        [
          "וי 1 תשתיות ואנרגיה פשה",
          15.862666512605006,
          44409
        ],
        [
          "נוי 2 תשתיות ואנרגיה פשה",
          84.02644187187657,
          44409
        ],
        [
          "יסודות2",
          1033.1288121799998,
          45658
        ],
        [
          "COPIA",
          70.8202775,
          46508
        ],
        [
          "ARES 4",
          0.0,
          44795
        ],
        [
          "Alto 2",
          0.0,
          42979
        ],
        [
          "AVENUE 3",
          0.0,
          43544
        ],
        [
          "בראק",
          0.0,
          43544
        ],
        [
          "נוי פסולת לאנרגיה - שותפות 1",
          0.0,
          "עד למועד פירוק שותפות"
        ],
        [
          "נוי פסולת לאנרגיה - שותפות 2",
          0.0,
          "עד למועד פירוק שותפות"
        ],
        [
          "דנמרק IPDS P S",
          0.0,
          43435
        ],
        [
          "ICG ASIA PASIFIC",
          0.0,
          45444
        ],
        [
          "ICG NORTH AMERICA",
          0.0,
          45413
        ],
        [
          "Kreos Capital",
          0.0,
          45931
        ],
        [
          "NETZ",
          0.0,
          43709
        ],
        [
          "Qumra",
          0.0,
          44562
        ],
        [
          "STAGE ONE 2",
          0.0,
          44562
        ],
        [
          "ANACAP",
          92.18623718304445,
          45047
        ],
        [
          "הלוואה 47 05/2018 הלוואה אנרג'יאן",
          2814.15,
          44532
        ],
        [
          "הלוואה 35 04/2017 -  מלון הית'רו לונדון",
          369.9085867754724,
          43554
        ],
        [
          "הלוואה ל- Long Island City הלוואה 37 08/2017",
          628.5355972896001,
          44012
        ],
        [
          "פרספטיב",
          0.0,
          "עד למועד פירוק שותפות"
        ],
        [
          "MIDEAL",
          0.0,
          46357
        ],
        [
          "CRESCENT",
          418.22612454,
          44531
        ],
        [
          "ICG SECONDARIES FUND",
          19.678399999999996,
          45807
        ],
        [
          "SIGNAL",
          30.394871183645854,
          45901
        ],
        [
          "INVESTCORP",
          226.23569038145342,
          45169
        ],
        [
          "STAGE ONE 3",
          26.509091400000003,
          46621
        ],
        [
          "AP PARTNERS",
          551.0803932736001,
          44585
        ]
      ]
    }
  }
}